{
  "batch_id": 5,
  "start_idx": 272,
  "end_idx": 340,
  "count": 68,
  "items": [
    {
      "id": "tieba_comments_241",
      "platform": "tieba",
      "file_type": "comments",
      "text": "让他们赢吧，锁妖塔倒了魔气泄露有你们好受的。还不如跟着它们吹吹捧捧，回家依旧各玩各的，大家都好。",
      "raw_data": {
        "comment_id": "153471434222",
        "parent_comment_id": "",
        "content": "让他们赢吧，锁妖塔倒了魔气泄露有你们好受的。还不如跟着它们吹吹捧捧，回家依旧各玩各的，大家都好。",
        "user_link": "https://tieba.baidu.com/home/main?id=tb.1.cb7fc855.Btk9-kXIPW6rvDE5f9affw%3Ft%3D1778148633",
        "user_nickname": "过把感情瘾º👻",
        "user_avatar": "https://gss0.bdstatic.com/6LZ1dD3d1sgCo2Kml5_Y_D3/sys/portrait/item/tb.1.cb7fc855.Btk9-kXIPW6rvDE5f9affw?t=1778148633",
        "publish_time": "2026-04-30 19:01:52",
        "ip_location": "安徽",
        "sub_comment_count": 2,
        "note_id": "10680204556",
        "note_url": "https://tieba.baidu.com/p/10680204556",
        "tieba_id": "24920884",
        "tieba_name": "王者荣耀世界吧",
        "tieba_link": "https://tieba.baidu.com/f?kw=%E7%8E%8B%E8%80%85%E8%8D%A3%E8%80%80%E4%B8%96%E7%95%8C",
        "last_modify_ts": 1778148633506
      }
    },
    {
      "id": "tieba_comments_242",
      "platform": "tieba",
      "file_type": "comments",
      "text": "看到说浴血全通无伤就是云玩家了，燕云的浴血是指最高难度的大世界首通，根本没有无伤的统计，而如果是无伤的话指的是挑战里面重复打的鬼神愁无伤，如果有人把每个怪都打了无伤，那多半是不屑于提浴血两个字的，直接说全boss无伤好了，因为无伤的难度远大于初见的浴血难度",
      "raw_data": {
        "comment_id": "153471271000",
        "parent_comment_id": "",
        "content": "看到说浴血全通无伤就是云玩家了，燕云的浴血是指最高难度的大世界首通，根本没有无伤的统计，而如果是无伤的话指的是挑战里面重复打的鬼神愁无伤，如果有人把每个怪都打了无伤，那多半是不屑于提浴血两个字的，直接说全boss无伤好了，因为无伤的难度远大于初见的浴血难度",
        "user_link": "https://tieba.baidu.com/home/main?id=tb.1.a64358a7.FEyAhCiUaIHx2B_ocCYgug%3Ft%3D1778148633",
        "user_nickname": "育碧-东京",
        "user_avatar": "https://gss0.bdstatic.com/6LZ1dD3d1sgCo2Kml5_Y_D3/sys/portrait/item/tb.1.a64358a7.FEyAhCiUaIHx2B_ocCYgug?t=1778148633",
        "publish_time": "2026-04-30 17:56:17",
        "ip_location": "广东",
        "sub_comment_count": 4,
        "note_id": "10680204556",
        "note_url": "https://tieba.baidu.com/p/10680204556",
        "tieba_id": "24920884",
        "tieba_name": "王者荣耀世界吧",
        "tieba_link": "https://tieba.baidu.com/f?kw=%E7%8E%8B%E8%80%85%E8%8D%A3%E8%80%80%E4%B8%96%E7%95%8C",
        "last_modify_ts": 1778148633507
      }
    },
    {
      "id": "tieba_comments_243",
      "platform": "tieba",
      "file_type": "comments",
      "text": "虽然王者玩的少，我还是渣渣没时间玩，燕云3000多小时还是有些资格说下的 就单纯战斗而言，燕云比王者差了至少两个层次😂，画风各有各的好，王者看起来整体更加清爽，燕云看起来更复杂，不过就风景而言燕云还是做的好些，不过材质精细度我反而觉得王者做的更好点，但是有些说不通呀，王者这么小素材材质应该更低才对，有么有大手解释下image_emoticon16 然后就是光影燕云拉中拉，我特么最不能忍的就是这个批打光，真恶心🤢，王者的打光好很多光影很好，不过王者看起来人物走路这块啥的总给我一种很轻浮的感觉，就轻飘飘的，这点燕云做的更好，时装两边都一般，剧情燕云更好些，配音燕云好很多，主要是王者念台词像是ai没有一点感情😑 其他我觉得这两个游戏都是不错的，可以都玩玩嘛。不用那么拼都是大世界游戏，慢慢玩就行了嘛image_emoticon66",
      "raw_data": {
        "comment_id": "153490102838",
        "parent_comment_id": "",
        "content": "虽然王者玩的少，我还是渣渣没时间玩，燕云3000多小时还是有些资格说下的 就单纯战斗而言，燕云比王者差了至少两个层次😂，画风各有各的好，王者看起来整体更加清爽，燕云看起来更复杂，不过就风景而言燕云还是做的好些，不过材质精细度我反而觉得王者做的更好点，但是有些说不通呀，王者这么小素材材质应该更低才对，有么有大手解释下image_emoticon16 然后就是光影燕云拉中拉，我特么最不能忍的就是这个批打光，真恶心🤢，王者的打光好很多光影很好，不过王者看起来人物走路这块啥的总给我一种很轻浮的感觉，就轻飘飘的，这点燕云做的更好，时装两边都一般，剧情燕云更好些，配音燕云好很多，主要是王者念台词像是ai没有一点感情😑 其他我觉得这两个游戏都是不错的，可以都玩玩嘛。不用那么拼都是大世界游戏，慢慢玩就行了嘛image_emoticon66",
        "user_link": "https://tieba.baidu.com/home/main?id=tb.1.97801b52.q-Lnb59XrCk8q9EdUmHqjw%3Ft%3D1778148633",
        "user_nickname": "哈密小白✨",
        "user_avatar": "https://gss0.bdstatic.com/6LZ1dD3d1sgCo2Kml5_Y_D3/sys/portrait/item/tb.1.97801b52.q-Lnb59XrCk8q9EdUmHqjw?t=1778148633",
        "publish_time": "2026-05-06 19:07:18",
        "ip_location": "四川",
        "sub_comment_count": 0,
        "note_id": "10680204556",
        "note_url": "https://tieba.baidu.com/p/10680204556",
        "tieba_id": "24920884",
        "tieba_name": "王者荣耀世界吧",
        "tieba_link": "https://tieba.baidu.com/f?kw=%E7%8E%8B%E8%80%85%E8%8D%A3%E8%80%80%E4%B8%96%E7%95%8C",
        "last_modify_ts": 1778148633507
      }
    },
    {
      "id": "tieba_comments_244",
      "platform": "tieba",
      "file_type": "comments",
      "text": "浴血无伤是不可能的，因为浴血是剧情难度，Boss打完就没了，你总不可能初见无伤吧？",
      "raw_data": {
        "comment_id": "153489885709",
        "parent_comment_id": "",
        "content": "浴血无伤是不可能的，因为浴血是剧情难度，Boss打完就没了，你总不可能初见无伤吧？",
        "user_link": "https://tieba.baidu.com/home/main?id=tb.1.b7bdb2aa.Wi03gpUYWFgsZ1f9do_vdA%3Ft%3D1778148633",
        "user_nickname": "无敌小火龙啊",
        "user_avatar": "https://gss0.bdstatic.com/6LZ1dD3d1sgCo2Kml5_Y_D3/sys/portrait/item/tb.1.b7bdb2aa.Wi03gpUYWFgsZ1f9do_vdA?t=1778148633",
        "publish_time": "2026-05-06 17:52:23",
        "ip_location": "江苏",
        "sub_comment_count": 0,
        "note_id": "10680204556",
        "note_url": "https://tieba.baidu.com/p/10680204556",
        "tieba_id": "24920884",
        "tieba_name": "王者荣耀世界吧",
        "tieba_link": "https://tieba.baidu.com/f?kw=%E7%8E%8B%E8%80%85%E8%8D%A3%E8%80%80%E4%B8%96%E7%95%8C",
        "last_modify_ts": 1778148633507
      }
    },
    {
      "id": "tieba_comments_245",
      "platform": "tieba",
      "file_type": "comments",
      "text": "根据饭圈定理，用一个游戏拉踩另一个游戏的，八成2个游戏都不玩。",
      "raw_data": {
        "comment_id": "153488333250",
        "parent_comment_id": "",
        "content": "根据饭圈定理，用一个游戏拉踩另一个游戏的，八成2个游戏都不玩。",
        "user_link": "https://tieba.baidu.com/home/main?id=tb.1.dc44cef6.8-7K7fFw9sjpwJcZxcByEw%3Ft%3D1778148633",
        "user_nickname": "zrgwater2",
        "user_avatar": "https://gss0.bdstatic.com/6LZ1dD3d1sgCo2Kml5_Y_D3/sys/portrait/item/tb.1.dc44cef6.8-7K7fFw9sjpwJcZxcByEw?t=1778148633",
        "publish_time": "2026-05-06 08:44:00",
        "ip_location": "江苏",
        "sub_comment_count": 0,
        "note_id": "10680204556",
        "note_url": "https://tieba.baidu.com/p/10680204556",
        "tieba_id": "24920884",
        "tieba_name": "王者荣耀世界吧",
        "tieba_link": "https://tieba.baidu.com/f?kw=%E7%8E%8B%E8%80%85%E8%8D%A3%E8%80%80%E4%B8%96%E7%95%8C",
        "last_modify_ts": 1778148633507
      }
    },
    {
      "id": "tieba_comments_246",
      "platform": "tieba",
      "file_type": "comments",
      "text": "纯扯蛋，我浴血就能打几个无伤，来王师姐单人内容嘎嘎乱杀，燕云卸势大概就是0.1秒的容错，这王师姐闪避全程无敌，至少0.3秒往上。",
      "raw_data": {
        "comment_id": "153488036317",
        "parent_comment_id": "",
        "content": "纯扯蛋，我浴血就能打几个无伤，来王师姐单人内容嘎嘎乱杀，燕云卸势大概就是0.1秒的容错，这王师姐闪避全程无敌，至少0.3秒往上。",
        "user_link": "https://tieba.baidu.com/home/main?id=tb.1.bb329f20.yC0l7mdrUQz3BxN2LlOXeQ%3Ft%3D1778148633",
        "user_nickname": "深澜岁月",
        "user_avatar": "https://gss0.bdstatic.com/6LZ1dD3d1sgCo2Kml5_Y_D3/sys/portrait/item/tb.1.bb329f20.yC0l7mdrUQz3BxN2LlOXeQ?t=1778148633",
        "publish_time": "2026-05-06 04:53:45",
        "ip_location": "四川",
        "sub_comment_count": 0,
        "note_id": "10680204556",
        "note_url": "https://tieba.baidu.com/p/10680204556",
        "tieba_id": "24920884",
        "tieba_name": "王者荣耀世界吧",
        "tieba_link": "https://tieba.baidu.com/f?kw=%E7%8E%8B%E8%80%85%E8%8D%A3%E8%80%80%E4%B8%96%E7%95%8C",
        "last_modify_ts": 1778148633507
      }
    },
    {
      "id": "tieba_comments_247",
      "platform": "tieba",
      "file_type": "comments",
      "text": "当时不想污染电脑，用手机搓玻璃过的，你伽神力",
      "raw_data": {
        "comment_id": "153484716915",
        "parent_comment_id": "",
        "content": "当时不想污染电脑，用手机搓玻璃过的，你伽神力",
        "user_link": "https://tieba.baidu.com/home/main?id=tb.1.8a114622.byAONNE6jcybegGTmntQRQ%3Ft%3D1778148633",
        "user_nickname": "此菡",
        "user_avatar": "https://gss0.bdstatic.com/6LZ1dD3d1sgCo2Kml5_Y_D3/sys/portrait/item/tb.1.8a114622.byAONNE6jcybegGTmntQRQ?t=1778148633",
        "publish_time": "2026-05-05 02:08:34",
        "ip_location": "山东",
        "sub_comment_count": 0,
        "note_id": "10680204556",
        "note_url": "https://tieba.baidu.com/p/10680204556",
        "tieba_id": "24920884",
        "tieba_name": "王者荣耀世界吧",
        "tieba_link": "https://tieba.baidu.com/f?kw=%E7%8E%8B%E8%80%85%E8%8D%A3%E8%80%80%E4%B8%96%E7%95%8C",
        "last_modify_ts": 1778148633508
      }
    },
    {
      "id": "tieba_comments_248",
      "platform": "tieba",
      "file_type": "comments",
      "text": "这人什么憨憨，我燕云辅助卸式的自动看剧情的玩家怎么打红buff很好打啊。什么浴血代打的吗？",
      "raw_data": {
        "comment_id": "153475474447",
        "parent_comment_id": "",
        "content": "这人什么憨憨，我燕云辅助卸式的自动看剧情的玩家怎么打红buff很好打啊。什么浴血代打的吗？",
        "user_link": "https://tieba.baidu.com/home/main?id=tb.1.68419b31.R6DeR31WP8Nkpa8r4xAizg%3Ft%3D1778148633",
        "user_nickname": "小刀@小剑",
        "user_avatar": "https://gss0.bdstatic.com/6LZ1dD3d1sgCo2Kml5_Y_D3/sys/portrait/item/tb.1.68419b31.R6DeR31WP8Nkpa8r4xAizg?t=1778148633",
        "publish_time": "2026-05-02 01:09:11",
        "ip_location": "上海",
        "sub_comment_count": 0,
        "note_id": "10680204556",
        "note_url": "https://tieba.baidu.com/p/10680204556",
        "tieba_id": "24920884",
        "tieba_name": "王者荣耀世界吧",
        "tieba_link": "https://tieba.baidu.com/f?kw=%E7%8E%8B%E8%80%85%E8%8D%A3%E8%80%80%E4%B8%96%E7%95%8C",
        "last_modify_ts": 1778148633508
      }
    },
    {
      "id": "tieba_comments_249",
      "platform": "tieba",
      "file_type": "comments",
      "text": "上一个开局报菜名的玩家群体是什么都忘了吗？这才六年啊image_emoticon22动脑子思考这种人说的话纯浪费思考时间",
      "raw_data": {
        "comment_id": "153474191707",
        "parent_comment_id": "",
        "content": "上一个开局报菜名的玩家群体是什么都忘了吗？这才六年啊image_emoticon22动脑子思考这种人说的话纯浪费思考时间",
        "user_link": "https://tieba.baidu.com/home/main?id=tb.1.60ec0c02.4C27RpXDF2wOdMOrXnq0TA%3Ft%3D1778148633",
        "user_nickname": "某人◆◆",
        "user_avatar": "https://gss0.bdstatic.com/6LZ1dD3d1sgCo2Kml5_Y_D3/sys/portrait/item/tb.1.60ec0c02.4C27RpXDF2wOdMOrXnq0TA?t=1778148633",
        "publish_time": "2026-05-01 17:19:32",
        "ip_location": "广东",
        "sub_comment_count": 0,
        "note_id": "10680204556",
        "note_url": "https://tieba.baidu.com/p/10680204556",
        "tieba_id": "24920884",
        "tieba_name": "王者荣耀世界吧",
        "tieba_link": "https://tieba.baidu.com/f?kw=%E7%8E%8B%E8%80%85%E8%8D%A3%E8%80%80%E4%B8%96%E7%95%8C",
        "last_modify_ts": 1778148633508
      }
    },
    {
      "id": "tieba_comments_250",
      "platform": "tieba",
      "file_type": "comments",
      "text": "扯淡呢，浴血全通不难，但不少BOSS要打多次，就是因为要背板，本人3K小时燕云，浴血小号都50层了。红BUFF难度低多了，这种人不管是帖子还是主播直接拉黑，因为他嘴里没真话。",
      "raw_data": {
        "comment_id": "153473824471",
        "parent_comment_id": "",
        "content": "扯淡呢，浴血全通不难，但不少BOSS要打多次，就是因为要背板，本人3K小时燕云，浴血小号都50层了。红BUFF难度低多了，这种人不管是帖子还是主播直接拉黑，因为他嘴里没真话。",
        "user_link": "https://tieba.baidu.com/home/main?id=tb.1.105b476e.ciVIVDoWbvrjDXvKXNnkXA%3Ft%3D1778148633",
        "user_nickname": "快乐的大脚1125",
        "user_avatar": "https://gss0.bdstatic.com/6LZ1dD3d1sgCo2Kml5_Y_D3/sys/portrait/item/tb.1.105b476e.ciVIVDoWbvrjDXvKXNnkXA?t=1778148633",
        "publish_time": "2026-05-01 14:49:40",
        "ip_location": "四川",
        "sub_comment_count": 0,
        "note_id": "10680204556",
        "note_url": "https://tieba.baidu.com/p/10680204556",
        "tieba_id": "24920884",
        "tieba_name": "王者荣耀世界吧",
        "tieba_link": "https://tieba.baidu.com/f?kw=%E7%8E%8B%E8%80%85%E8%8D%A3%E8%80%80%E4%B8%96%E7%95%8C",
        "last_modify_ts": 1778148633508
      }
    },
    {
      "id": "tieba_comments_251",
      "platform": "tieba",
      "file_type": "comments",
      "text": "你说得对，只有3.0抽了2命大黑塔的人，才叫爽玩3.0-3.2，否则玩得太憋屈了。",
      "raw_data": {
        "comment_id": "153439769963",
        "parent_comment_id": "",
        "content": "你说得对，只有3.0抽了2命大黑塔的人，才叫爽玩3.0-3.2，否则玩得太憋屈了。",
        "user_link": "https://tieba.baidu.com/home/main?id=tb.1.41d37543.PjwNi4DwLC9dWqcyNjqS3g%3Ft%3D1778148637",
        "user_nickname": "🐔只因你太美℃",
        "user_avatar": "https://gss0.bdstatic.com/6LZ1dD3d1sgCo2Kml5_Y_D3/sys/portrait/item/tb.1.41d37543.PjwNi4DwLC9dWqcyNjqS3g?t=1778148637",
        "publish_time": "2026-04-21 08:09:14",
        "ip_location": "浙江",
        "sub_comment_count": 12,
        "note_id": "10655845051",
        "note_url": "https://tieba.baidu.com/p/10655845051",
        "tieba_id": "27752863",
        "tieba_name": "崩坏星穹铁道内鬼吧",
        "tieba_link": "https://tieba.baidu.com/f?kw=%E5%B4%A9%E5%9D%8F%E6%98%9F%E7%A9%B9%E9%93%81%E9%81%93%E5%86%85%E9%AC%BC",
        "last_modify_ts": 1778148637772
      }
    },
    {
      "id": "tieba_comments_252",
      "platform": "tieba",
      "file_type": "comments",
      "text": "强度党就应该追求当前最强，根本不会参与欢愉和记忆的斗争，除非新人，不然没有蝶风三昔不配当强度党，狼售后真的更强，那就就再抽狼。抽不起？没钱不要当强度党，那只是在找存在。",
      "raw_data": {
        "comment_id": "153440120384",
        "parent_comment_id": "",
        "content": "强度党就应该追求当前最强，根本不会参与欢愉和记忆的斗争，除非新人，不然没有蝶风三昔不配当强度党，狼售后真的更强，那就就再抽狼。抽不起？没钱不要当强度党，那只是在找存在。",
        "user_link": "https://tieba.baidu.com/home/main?id=tb.1.600e9ec1.yhIVpJXjFPrt0GwCC0eniw%3Ft%3D1778148637",
        "user_nickname": "eicvfg",
        "user_avatar": "https://gss0.bdstatic.com/6LZ1dD3d1sgCo2Kml5_Y_D3/sys/portrait/item/tb.1.600e9ec1.yhIVpJXjFPrt0GwCC0eniw?t=1778148637",
        "publish_time": "2026-04-21 10:14:02",
        "ip_location": "广东",
        "sub_comment_count": 2,
        "note_id": "10655845051",
        "note_url": "https://tieba.baidu.com/p/10655845051",
        "tieba_id": "27752863",
        "tieba_name": "崩坏星穹铁道内鬼吧",
        "tieba_link": "https://tieba.baidu.com/f?kw=%E5%B4%A9%E5%9D%8F%E6%98%9F%E7%A9%B9%E9%93%81%E9%81%93%E5%86%85%E9%AC%BC",
        "last_modify_ts": 1778148637772
      }
    },
    {
      "id": "tieba_comments_253",
      "platform": "tieba",
      "file_type": "comments",
      "text": "你能说出xp党占比百分之90真是无敌了。。。你猜猜如果有百分之90是xp党，主推这个说法能流行起来吗？",
      "raw_data": {
        "comment_id": "153440925151",
        "parent_comment_id": "",
        "content": "你能说出xp党占比百分之90真是无敌了。。。你猜猜如果有百分之90是xp党，主推这个说法能流行起来吗？",
        "user_link": "https://tieba.baidu.com/home/main?id=tb.1.f94f893e.0FK1eNN-lQ0dsLem-wxclw%3Ft%3D1778148637",
        "user_nickname": "爱纳尼什么情况",
        "user_avatar": "https://gss0.bdstatic.com/6LZ1dD3d1sgCo2Kml5_Y_D3/sys/portrait/item/tb.1.f94f893e.0FK1eNN-lQ0dsLem-wxclw?t=1778148637",
        "publish_time": "2026-04-21 14:52:38",
        "ip_location": "四川",
        "sub_comment_count": 0,
        "note_id": "10655845051",
        "note_url": "https://tieba.baidu.com/p/10655845051",
        "tieba_id": "27752863",
        "tieba_name": "崩坏星穹铁道内鬼吧",
        "tieba_link": "https://tieba.baidu.com/f?kw=%E5%B4%A9%E5%9D%8F%E6%98%9F%E7%A9%B9%E9%93%81%E9%81%93%E5%86%85%E9%AC%BC",
        "last_modify_ts": 1778148637773
      }
    },
    {
      "id": "tieba_comments_254",
      "platform": "tieba",
      "file_type": "comments",
      "text": "我摊牌，我是强度党，仓库技给绯英我就抽绯了，现在准备抽狼",
      "raw_data": {
        "comment_id": "153440455183",
        "parent_comment_id": "",
        "content": "我摊牌，我是强度党，仓库技给绯英我就抽绯了，现在准备抽狼",
        "user_link": "https://tieba.baidu.com/home/main?id=tb.1.65b5ceff.26QWvUmy1O3vNO6O0vhcjg%3Ft%3D1778148637",
        "user_nickname": "罹情易美",
        "user_avatar": "https://gss0.bdstatic.com/6LZ1dD3d1sgCo2Kml5_Y_D3/sys/portrait/item/tb.1.65b5ceff.26QWvUmy1O3vNO6O0vhcjg?t=1778148637",
        "publish_time": "2026-04-21 12:03:54",
        "ip_location": "江苏",
        "sub_comment_count": 0,
        "note_id": "10655845051",
        "note_url": "https://tieba.baidu.com/p/10655845051",
        "tieba_id": "27752863",
        "tieba_name": "崩坏星穹铁道内鬼吧",
        "tieba_link": "https://tieba.baidu.com/f?kw=%E5%B4%A9%E5%9D%8F%E6%98%9F%E7%A9%B9%E9%93%81%E9%81%93%E5%86%85%E9%AC%BC",
        "last_modify_ts": 1778148637773
      }
    },
    {
      "id": "tieba_comments_255",
      "platform": "tieba",
      "file_type": "comments",
      "text": "image_emoticon221.0那是有的，后面全被策划教育老实了",
      "raw_data": {
        "comment_id": "153440064652",
        "parent_comment_id": "",
        "content": "image_emoticon221.0那是有的，后面全被策划教育老实了",
        "user_link": "https://tieba.baidu.com/home/main?id=tb.1.957bb4ba.1Kclry5g2JmJPaTC-nfG8g%3Ft%3D1778148637",
        "user_nickname": "和谐社会人",
        "user_avatar": "https://gss0.bdstatic.com/6LZ1dD3d1sgCo2Kml5_Y_D3/sys/portrait/item/tb.1.957bb4ba.1Kclry5g2JmJPaTC-nfG8g?t=1778148637",
        "publish_time": "2026-04-21 09:56:06",
        "ip_location": "浙江",
        "sub_comment_count": 0,
        "note_id": "10655845051",
        "note_url": "https://tieba.baidu.com/p/10655845051",
        "tieba_id": "27752863",
        "tieba_name": "崩坏星穹铁道内鬼吧",
        "tieba_link": "https://tieba.baidu.com/f?kw=%E5%B4%A9%E5%9D%8F%E6%98%9F%E7%A9%B9%E9%93%81%E9%81%93%E5%86%85%E9%AC%BC",
        "last_modify_ts": 1778148637774
      }
    },
    {
      "id": "tieba_comments_257",
      "platform": "tieba",
      "file_type": "comments",
      "text": "那我这种是什么，无论男女选强的，强度一样选女的",
      "raw_data": {
        "comment_id": "153439890567",
        "parent_comment_id": "",
        "content": "那我这种是什么，无论男女选强的，强度一样选女的",
        "user_link": "https://tieba.baidu.com/home/main?id=tb.1.468b3ea2.4Qpg-1QOK_vWk7oUlbZLTw%3Ft%3D1778148637",
        "user_nickname": "内切远射",
        "user_avatar": "https://gss0.bdstatic.com/6LZ1dD3d1sgCo2Kml5_Y_D3/sys/portrait/item/tb.1.468b3ea2.4Qpg-1QOK_vWk7oUlbZLTw?t=1778148637",
        "publish_time": "2026-04-21 08:55:08",
        "ip_location": "广东",
        "sub_comment_count": 0,
        "note_id": "10655845051",
        "note_url": "https://tieba.baidu.com/p/10655845051",
        "tieba_id": "27752863",
        "tieba_name": "崩坏星穹铁道内鬼吧",
        "tieba_link": "https://tieba.baidu.com/f?kw=%E5%B4%A9%E5%9D%8F%E6%98%9F%E7%A9%B9%E9%93%81%E9%81%93%E5%86%85%E9%AC%BC",
        "last_modify_ts": 1778148637774
      }
    },
    {
      "id": "tieba_comments_258",
      "platform": "tieba",
      "file_type": "comments",
      "text": "同意，假设先21狼火爻爽到4.7，然后虚照出来，如果21虚照踢火或踢爻做不到提升120%，那不如直接把这4金加给银狼直接61，提升也有120%。",
      "raw_data": {
        "comment_id": "153439791470",
        "parent_comment_id": "",
        "content": "同意，假设先21狼火爻爽到4.7，然后虚照出来，如果21虚照踢火或踢爻做不到提升120%，那不如直接把这4金加给银狼直接61，提升也有120%。",
        "user_link": "https://tieba.baidu.com/home/main?id=tb.1.901029bd.3YJHVachTXKcZTF9G7vmjw%3Ft%3D1778148637",
        "user_nickname": "永远的深蓝898",
        "user_avatar": "https://gss0.bdstatic.com/6LZ1dD3d1sgCo2Kml5_Y_D3/sys/portrait/item/tb.1.901029bd.3YJHVachTXKcZTF9G7vmjw?t=1778148637",
        "publish_time": "2026-04-21 08:18:10",
        "ip_location": "江苏",
        "sub_comment_count": 0,
        "note_id": "10655845051",
        "note_url": "https://tieba.baidu.com/p/10655845051",
        "tieba_id": "27752863",
        "tieba_name": "崩坏星穹铁道内鬼吧",
        "tieba_link": "https://tieba.baidu.com/f?kw=%E5%B4%A9%E5%9D%8F%E6%98%9F%E7%A9%B9%E9%93%81%E9%81%93%E5%86%85%E9%AC%BC",
        "last_modify_ts": 1778148637775
      }
    },
    {
      "id": "tieba_comments_259",
      "platform": "tieba",
      "file_type": "comments",
      "text": "说得对image_emoticon",
      "raw_data": {
        "comment_id": "153439773968",
        "parent_comment_id": "",
        "content": "说得对image_emoticon",
        "user_link": "https://tieba.baidu.com/home/main?id=tb.1.77d82852.ULCzPWcSGdkfxrwRveJ74g%3Ft%3D1778148637",
        "user_nickname": "粉蓝少女",
        "user_avatar": "https://gss0.bdstatic.com/6LZ1dD3d1sgCo2Kml5_Y_D3/sys/portrait/item/tb.1.77d82852.ULCzPWcSGdkfxrwRveJ74g?t=1778148637",
        "publish_time": "2026-04-21 08:10:55",
        "ip_location": "湖南",
        "sub_comment_count": 0,
        "note_id": "10655845051",
        "note_url": "https://tieba.baidu.com/p/10655845051",
        "tieba_id": "27752863",
        "tieba_name": "崩坏星穹铁道内鬼吧",
        "tieba_link": "https://tieba.baidu.com/f?kw=%E5%B4%A9%E5%9D%8F%E6%98%9F%E7%A9%B9%E9%93%81%E9%81%93%E5%86%85%E9%AC%BC",
        "last_modify_ts": 1778148637775
      }
    },
    {
      "id": "tieba_comments_260",
      "platform": "tieba",
      "file_type": "comments",
      "text": "然而铁会为XP抽卡能有多少呢，最终还不是为强度买单，弃子就是流水低，主推就是流水高",
      "raw_data": {
        "comment_id": "153439943634",
        "parent_comment_id": "",
        "content": "然而铁会为XP抽卡能有多少呢，最终还不是为强度买单，弃子就是流水低，主推就是流水高",
        "user_link": "https://tieba.baidu.com/home/main?id=tb.1.4eea06ef.ziRaRA2HqZ6w-e9D0-ew-A%3Ft%3D1778148637",
        "user_nickname": "是一天又一天♬",
        "user_avatar": "https://gss0.bdstatic.com/6LZ1dD3d1sgCo2Kml5_Y_D3/sys/portrait/item/tb.1.4eea06ef.ziRaRA2HqZ6w-e9D0-ew-A?t=1778148637",
        "publish_time": "2026-04-21 09:14:02",
        "ip_location": "江西",
        "sub_comment_count": 0,
        "note_id": "10655845051",
        "note_url": "https://tieba.baidu.com/p/10655845051",
        "tieba_id": "27752863",
        "tieba_name": "崩坏星穹铁道内鬼吧",
        "tieba_link": "https://tieba.baidu.com/f?kw=%E5%B4%A9%E5%9D%8F%E6%98%9F%E7%A9%B9%E9%93%81%E9%81%93%E5%86%85%E9%AC%BC",
        "last_modify_ts": 1778148637775
      }
    },
    {
      "id": "tieba_comments_261",
      "platform": "tieba",
      "file_type": "comments",
      "text": "image_emoticon68",
      "raw_data": {
        "comment_id": "124308519266",
        "parent_comment_id": "",
        "content": "image_emoticon68",
        "user_link": "https://tieba.baidu.com/home/main?id=tb.1.45edae63.k2matQAwHlFhcLen9_Vjfg%3Ft%3D1778148647",
        "user_nickname": "剧团砍价刀",
        "user_avatar": "https://gss0.bdstatic.com/6LZ1dD3d1sgCo2Kml5_Y_D3/sys/portrait/item/tb.1.45edae63.k2matQAwHlFhcLen9_Vjfg?t=1778148647",
        "publish_time": "2019-02-27 10:14:19",
        "ip_location": "北京",
        "sub_comment_count": 0,
        "note_id": "6049200095",
        "note_url": "https://tieba.baidu.com/p/6049200095",
        "tieba_id": "26400252",
        "tieba_name": "iphonexr吧",
        "tieba_link": "https://tieba.baidu.com/f?kw=iphonexr",
        "last_modify_ts": 1778148647282
      }
    },
    {
      "id": "tieba_comments_262",
      "platform": "tieba",
      "file_type": "comments",
      "text": "但是戴口罩人脸就不行了。。",
      "raw_data": {
        "comment_id": "124308572067",
        "parent_comment_id": "",
        "content": "但是戴口罩人脸就不行了。。",
        "user_link": "https://tieba.baidu.com/home/main?id=tb.1.85c71212.nwzlH6RX_tknsVX6S7U8Dw%3Ft%3D1778148647",
        "user_nickname": "krotos1234",
        "user_avatar": "https://gss0.bdstatic.com/6LZ1dD3d1sgCo2Kml5_Y_D3/sys/portrait/item/tb.1.85c71212.nwzlH6RX_tknsVX6S7U8Dw?t=1778148647",
        "publish_time": "2019-02-27 10:18:05",
        "ip_location": "天津",
        "sub_comment_count": 25,
        "note_id": "6049200095",
        "note_url": "https://tieba.baidu.com/p/6049200095",
        "tieba_id": "26400252",
        "tieba_name": "iphonexr吧",
        "tieba_link": "https://tieba.baidu.com/f?kw=iphonexr",
        "last_modify_ts": 1778148647283
      }
    },
    {
      "id": "tieba_comments_263",
      "platform": "tieba",
      "file_type": "comments",
      "text": "image_emoticon25",
      "raw_data": {
        "comment_id": "124308583673",
        "parent_comment_id": "",
        "content": "image_emoticon25",
        "user_link": "https://tieba.baidu.com/home/main?id=tb.1.5ce55418.Qkfruk_MREqYl2mL8bVQVg%3Ft%3D1778148647",
        "user_nickname": "MORIECHO",
        "user_avatar": "https://gss0.bdstatic.com/6LZ1dD3d1sgCo2Kml5_Y_D3/sys/portrait/item/tb.1.5ce55418.Qkfruk_MREqYl2mL8bVQVg?t=1778148647",
        "publish_time": "2019-02-27 10:18:55",
        "ip_location": "",
        "sub_comment_count": 0,
        "note_id": "6049200095",
        "note_url": "https://tieba.baidu.com/p/6049200095",
        "tieba_id": "26400252",
        "tieba_name": "iphonexr吧",
        "tieba_link": "https://tieba.baidu.com/f?kw=iphonexr",
        "last_modify_ts": 1778148647283
      }
    },
    {
      "id": "tieba_comments_264",
      "platform": "tieba",
      "file_type": "comments",
      "text": "续航感觉也一般，可能是我之前用的是红米note4x 4000mh大电池的缘故吧，没感觉xr电池多好",
      "raw_data": {
        "comment_id": "124308585527",
        "parent_comment_id": "",
        "content": "续航感觉也一般，可能是我之前用的是红米note4x 4000mh大电池的缘故吧，没感觉xr电池多好",
        "user_link": "https://tieba.baidu.com/home/main?id=tb.1.85c71212.nwzlH6RX_tknsVX6S7U8Dw%3Ft%3D1778148647",
        "user_nickname": "krotos1234",
        "user_avatar": "https://gss0.bdstatic.com/6LZ1dD3d1sgCo2Kml5_Y_D3/sys/portrait/item/tb.1.85c71212.nwzlH6RX_tknsVX6S7U8Dw?t=1778148647",
        "publish_time": "2019-02-27 10:19:03",
        "ip_location": "天津",
        "sub_comment_count": 18,
        "note_id": "6049200095",
        "note_url": "https://tieba.baidu.com/p/6049200095",
        "tieba_id": "26400252",
        "tieba_name": "iphonexr吧",
        "tieba_link": "https://tieba.baidu.com/f?kw=iphonexr",
        "last_modify_ts": 1778148647284
      }
    },
    {
      "id": "tieba_comments_265",
      "platform": "tieba",
      "file_type": "comments",
      "text": "XR唯一让我觉得遗憾的是，没有3Dtouch，习惯了二级菜单以后，没有了一时半会还没办法习惯。其他都不是问题",
      "raw_data": {
        "comment_id": "124308602622",
        "parent_comment_id": "",
        "content": "XR唯一让我觉得遗憾的是，没有3Dtouch，习惯了二级菜单以后，没有了一时半会还没办法习惯。其他都不是问题",
        "user_link": "https://tieba.baidu.com/home/main?id=tb.1.c7289a5e.d_qq1-uqKuuRPxAeP_WykQ%3Ft%3D1778148647",
        "user_nickname": "不吃香菜🍀🍀",
        "user_avatar": "https://gss0.bdstatic.com/6LZ1dD3d1sgCo2Kml5_Y_D3/sys/portrait/item/tb.1.c7289a5e.d_qq1-uqKuuRPxAeP_WykQ?t=1778148647",
        "publish_time": "2019-02-27 10:20:17",
        "ip_location": "广东",
        "sub_comment_count": 11,
        "note_id": "6049200095",
        "note_url": "https://tieba.baidu.com/p/6049200095",
        "tieba_id": "26400252",
        "tieba_name": "iphonexr吧",
        "tieba_link": "https://tieba.baidu.com/f?kw=iphonexr",
        "last_modify_ts": 1778148647284
      }
    },
    {
      "id": "tieba_comments_268",
      "platform": "tieba",
      "file_type": "comments",
      "text": "双卡信号还好吗？王者会不会460",
      "raw_data": {
        "comment_id": "124309885743",
        "parent_comment_id": "",
        "content": "双卡信号还好吗？王者会不会460",
        "user_link": "https://tieba.baidu.com/home/main?id=tb.1.7142a0dc.unMQtpaUv_OcuRfY43JoEA%3Ft%3D1778148647",
        "user_nickname": "长安亦难安",
        "user_avatar": "https://gss0.bdstatic.com/6LZ1dD3d1sgCo2Kml5_Y_D3/sys/portrait/item/tb.1.7142a0dc.unMQtpaUv_OcuRfY43JoEA?t=1778148647",
        "publish_time": "2019-02-27 11:46:31",
        "ip_location": "江苏",
        "sub_comment_count": 1,
        "note_id": "6049200095",
        "note_url": "https://tieba.baidu.com/p/6049200095",
        "tieba_id": "26400252",
        "tieba_name": "iphonexr吧",
        "tieba_link": "https://tieba.baidu.com/f?kw=iphonexr",
        "last_modify_ts": 1778148647285
      }
    },
    {
      "id": "tieba_comments_269",
      "platform": "tieba",
      "file_type": "comments",
      "text": "没用过3d touch的表示很喜欢xr",
      "raw_data": {
        "comment_id": "124310410462",
        "parent_comment_id": "",
        "content": "没用过3d touch的表示很喜欢xr",
        "user_link": "https://tieba.baidu.com/home/main?id=tb.1.459c66b6.mGlMojsATJJ6_-PU1BNhUQ%3Ft%3D1778148647",
        "user_nickname": "或许还是我",
        "user_avatar": "https://gss0.bdstatic.com/6LZ1dD3d1sgCo2Kml5_Y_D3/sys/portrait/item/tb.1.459c66b6.mGlMojsATJJ6_-PU1BNhUQ?t=1778148647",
        "publish_time": "2019-02-27 12:23:41",
        "ip_location": "河北",
        "sub_comment_count": 1,
        "note_id": "6049200095",
        "note_url": "https://tieba.baidu.com/p/6049200095",
        "tieba_id": "26400252",
        "tieba_name": "iphonexr吧",
        "tieba_link": "https://tieba.baidu.com/f?kw=iphonexr",
        "last_modify_ts": 1778148647285
      }
    },
    {
      "id": "tieba_comments_270",
      "platform": "tieba",
      "file_type": "comments",
      "text": "你是啥厂的电池啊老哥image_emoticon25",
      "raw_data": {
        "comment_id": "124310926739",
        "parent_comment_id": "",
        "content": "你是啥厂的电池啊老哥image_emoticon25",
        "user_link": "https://tieba.baidu.com/home/main?id=tb.1.5c277a86.nYQw18822z9GR0wzBGRS2w%3Ft%3D1778148647",
        "user_nickname": "iPhone🌜",
        "user_avatar": "https://gss0.bdstatic.com/6LZ1dD3d1sgCo2Kml5_Y_D3/sys/portrait/item/tb.1.5c277a86.nYQw18822z9GR0wzBGRS2w?t=1778148647",
        "publish_time": "2019-02-27 12:58:58",
        "ip_location": "",
        "sub_comment_count": 7,
        "note_id": "6049200095",
        "note_url": "https://tieba.baidu.com/p/6049200095",
        "tieba_id": "26400252",
        "tieba_name": "iphonexr吧",
        "tieba_link": "https://tieba.baidu.com/f?kw=iphonexr",
        "last_modify_ts": 1778148647285
      }
    },
    {
      "id": "tieba_comments_271",
      "platform": "tieba",
      "file_type": "comments",
      "text": "随便骂，我先把贴吧卸载一段时间image_emoticon",
      "raw_data": {
        "comment_id": "151940012087",
        "parent_comment_id": "",
        "content": "随便骂，我先把贴吧卸载一段时间image_emoticon",
        "user_link": "https://tieba.baidu.com/home/main?id=tb.1.c2413866.mT53bLHNmAJJhT227ugawA%3Ft%3D1778148653",
        "user_nickname": "Stray_insa",
        "user_avatar": "https://gss0.bdstatic.com/6LZ1dD3d1sgCo2Kml5_Y_D3/sys/portrait/item/tb.1.c2413866.mT53bLHNmAJJhT227ugawA?t=1778148653",
        "publish_time": "2025-04-10 17:41:00",
        "ip_location": "云南",
        "sub_comment_count": 8,
        "note_id": "9636099077",
        "note_url": "https://tieba.baidu.com/p/9636099077",
        "tieba_id": "16791220",
        "tieba_name": "火影忍者手游吧",
        "tieba_link": "https://tieba.baidu.com/f?kw=%E7%81%AB%E5%BD%B1%E5%BF%8D%E8%80%85%E6%89%8B%E6%B8%B8",
        "last_modify_ts": 1778148653642
      }
    },
    {
      "id": "tieba_comments_272",
      "platform": "tieba",
      "file_type": "comments",
      "text": "那你有没有想过以后的忍者也可以体验呢image_emoticon15",
      "raw_data": {
        "comment_id": "151940019648",
        "parent_comment_id": "",
        "content": "那你有没有想过以后的忍者也可以体验呢image_emoticon15",
        "user_link": "https://tieba.baidu.com/home/main?id=tb.1.7bfdc1a4.wKDBJ5YHurkIfqGym1DR5A%3Ft%3D1778148653",
        "user_nickname": "Ra1ynots",
        "user_avatar": "https://gss0.bdstatic.com/6LZ1dD3d1sgCo2Kml5_Y_D3/sys/portrait/item/tb.1.7bfdc1a4.wKDBJ5YHurkIfqGym1DR5A?t=1778148653",
        "publish_time": "2025-04-10 17:43:05",
        "ip_location": "山东",
        "sub_comment_count": 12,
        "note_id": "9636099077",
        "note_url": "https://tieba.baidu.com/p/9636099077",
        "tieba_id": "16791220",
        "tieba_name": "火影忍者手游吧",
        "tieba_link": "https://tieba.baidu.com/f?kw=%E7%81%AB%E5%BD%B1%E5%BF%8D%E8%80%85%E6%89%8B%E6%B8%B8",
        "last_modify_ts": 1778148653643
      }
    },
    {
      "id": "tieba_comments_273",
      "platform": "tieba",
      "file_type": "comments",
      "text": "我建议折中一下，改成高招，金币忍者，蓝卷忍者，和其他免费忍者全免费体验",
      "raw_data": {
        "comment_id": "151940026269",
        "parent_comment_id": "",
        "content": "我建议折中一下，改成高招，金币忍者，蓝卷忍者，和其他免费忍者全免费体验",
        "user_link": "https://tieba.baidu.com/home/main?id=tb.1.716ae71e.OBL8v3sV3my0aSSqz3fuxw%3Ft%3D1778148653",
        "user_nickname": "gdsrfghh",
        "user_avatar": "https://gss0.bdstatic.com/6LZ1dD3d1sgCo2Kml5_Y_D3/sys/portrait/item/tb.1.716ae71e.OBL8v3sV3my0aSSqz3fuxw?t=1778148653",
        "publish_time": "2025-04-10 17:44:52",
        "ip_location": "",
        "sub_comment_count": 12,
        "note_id": "9636099077",
        "note_url": "https://tieba.baidu.com/p/9636099077",
        "tieba_id": "16791220",
        "tieba_name": "火影忍者手游吧",
        "tieba_link": "https://tieba.baidu.com/f?kw=%E7%81%AB%E5%BD%B1%E5%BF%8D%E8%80%85%E6%89%8B%E6%B8%B8",
        "last_modify_ts": 1778148653643
      }
    },
    {
      "id": "tieba_comments_274",
      "platform": "tieba",
      "file_type": "comments",
      "text": "火影想更好留住新玩家角色试用肯定得开忍者数量太多了，不然萌新都分不清假后摇真后摇，还有某些忍者的技能和技能范围，上试用也行加个限制比如练习场一天只能试用3个忍者，火影还是主流忍者玩的多但打架能选三个，来个偏门忍者不奇怪",
      "raw_data": {
        "comment_id": "151940043698",
        "parent_comment_id": "",
        "content": "火影想更好留住新玩家角色试用肯定得开忍者数量太多了，不然萌新都分不清假后摇真后摇，还有某些忍者的技能和技能范围，上试用也行加个限制比如练习场一天只能试用3个忍者，火影还是主流忍者玩的多但打架能选三个，来个偏门忍者不奇怪",
        "user_link": "https://tieba.baidu.com/home/main?id=tb.1.edfe971d.BNrrUbQUepFvM3zek_qUbQ%3Ft%3D1778148653",
        "user_nickname": "峨芦",
        "user_avatar": "https://gss0.bdstatic.com/6LZ1dD3d1sgCo2Kml5_Y_D3/sys/portrait/item/tb.1.edfe971d.BNrrUbQUepFvM3zek_qUbQ?t=1778148653",
        "publish_time": "2025-04-10 17:49:36",
        "ip_location": "安徽",
        "sub_comment_count": 2,
        "note_id": "9636099077",
        "note_url": "https://tieba.baidu.com/p/9636099077",
        "tieba_id": "16791220",
        "tieba_name": "火影忍者手游吧",
        "tieba_link": "https://tieba.baidu.com/f?kw=%E7%81%AB%E5%BD%B1%E5%BF%8D%E8%80%85%E6%89%8B%E6%B8%B8",
        "last_modify_ts": 1778148653644
      }
    },
    {
      "id": "tieba_comments_275",
      "platform": "tieba",
      "file_type": "comments",
      "text": "我支持就行了，你可以闭嘴了",
      "raw_data": {
        "comment_id": "151940077287",
        "parent_comment_id": "",
        "content": "我支持就行了，你可以闭嘴了",
        "user_link": "https://tieba.baidu.com/home/main?id=tb.1.d1bb687.M5b2845tFZjtk9_Ln0WaEw%3Ft%3D1778148653",
        "user_nickname": "界王拳。。",
        "user_avatar": "https://gss0.bdstatic.com/6LZ1dD3d1sgCo2Kml5_Y_D3/sys/portrait/item/tb.1.d1bb687.M5b2845tFZjtk9_Ln0WaEw?t=1778148653",
        "publish_time": "2025-04-10 17:58:53",
        "ip_location": "广西",
        "sub_comment_count": 1,
        "note_id": "9636099077",
        "note_url": "https://tieba.baidu.com/p/9636099077",
        "tieba_id": "16791220",
        "tieba_name": "火影忍者手游吧",
        "tieba_link": "https://tieba.baidu.com/f?kw=%E7%81%AB%E5%BD%B1%E5%BF%8D%E8%80%85%E6%89%8B%E6%B8%B8",
        "last_modify_ts": 1778148653644
      }
    },
    {
      "id": "tieba_comments_277",
      "platform": "tieba",
      "file_type": "comments",
      "text": "无所谓，玩不下去退游就可以了，哪一天我玩不下去我会直接离开的",
      "raw_data": {
        "comment_id": "151940084346",
        "parent_comment_id": "",
        "content": "无所谓，玩不下去退游就可以了，哪一天我玩不下去我会直接离开的",
        "user_link": "https://tieba.baidu.com/home/main?id=tb.1.e77fe7e9.0lp6mQ0Iftirmmj374lFlw%3Ft%3D1778148653",
        "user_nickname": "rubyyy",
        "user_avatar": "https://gss0.bdstatic.com/6LZ1dD3d1sgCo2Kml5_Y_D3/sys/portrait/item/tb.1.e77fe7e9.0lp6mQ0Iftirmmj374lFlw?t=1778148653",
        "publish_time": "2025-04-10 18:00:48",
        "ip_location": "广东",
        "sub_comment_count": 0,
        "note_id": "9636099077",
        "note_url": "https://tieba.baidu.com/p/9636099077",
        "tieba_id": "16791220",
        "tieba_name": "火影忍者手游吧",
        "tieba_link": "https://tieba.baidu.com/f?kw=%E7%81%AB%E5%BD%B1%E5%BF%8D%E8%80%85%E6%89%8B%E6%B8%B8",
        "last_modify_ts": 1778148653645
      }
    },
    {
      "id": "tieba_comments_278",
      "platform": "tieba",
      "file_type": "comments",
      "text": "支持，凭什么我花了钱的别人可以白嫖，那些说别的游戏可以的那你就去玩别的游戏啊image_emoticon86",
      "raw_data": {
        "comment_id": "151940152881",
        "parent_comment_id": "",
        "content": "支持，凭什么我花了钱的别人可以白嫖，那些说别的游戏可以的那你就去玩别的游戏啊image_emoticon86",
        "user_link": "https://tieba.baidu.com/home/main?id=tb.1.350f3443.E0z2D1QIVd2TvHFjR3ipcg%3Ft%3D1778148653",
        "user_nickname": "相思风雨中🌼",
        "user_avatar": "https://gss0.bdstatic.com/6LZ1dD3d1sgCo2Kml5_Y_D3/sys/portrait/item/tb.1.350f3443.E0z2D1QIVd2TvHFjR3ipcg?t=1778148653",
        "publish_time": "2025-04-10 18:19:33",
        "ip_location": "广东",
        "sub_comment_count": 3,
        "note_id": "9636099077",
        "note_url": "https://tieba.baidu.com/p/9636099077",
        "tieba_id": "16791220",
        "tieba_name": "火影忍者手游吧",
        "tieba_link": "https://tieba.baidu.com/f?kw=%E7%81%AB%E5%BD%B1%E5%BF%8D%E8%80%85%E6%89%8B%E6%B8%B8",
        "last_modify_ts": 1778148653645
      }
    },
    {
      "id": "tieba_comments_279",
      "platform": "tieba",
      "file_type": "comments",
      "text": "贱不贱呀，非得等要死再开是吧",
      "raw_data": {
        "comment_id": "151940156993",
        "parent_comment_id": "",
        "content": "贱不贱呀，非得等要死再开是吧",
        "user_link": "https://tieba.baidu.com/home/main?id=tb.1.34cec3db.U1Kzls9-C5xZqRFVyTCVlg%3Ft%3D1778148653",
        "user_nickname": "羁绊之火🔥",
        "user_avatar": "https://gss0.bdstatic.com/6LZ1dD3d1sgCo2Kml5_Y_D3/sys/portrait/item/tb.1.34cec3db.U1Kzls9-C5xZqRFVyTCVlg?t=1778148653",
        "publish_time": "2025-04-10 18:20:41",
        "ip_location": "内蒙古",
        "sub_comment_count": 2,
        "note_id": "9636099077",
        "note_url": "https://tieba.baidu.com/p/9636099077",
        "tieba_id": "16791220",
        "tieba_name": "火影忍者手游吧",
        "tieba_link": "https://tieba.baidu.com/f?kw=%E7%81%AB%E5%BD%B1%E5%BF%8D%E8%80%85%E6%89%8B%E6%B8%B8",
        "last_modify_ts": 1778148653646
      }
    },
    {
      "id": "tieba_comments_280",
      "platform": "tieba",
      "file_type": "comments",
      "text": "忍者数量增多迟早会开，希望别看到要死了才开。",
      "raw_data": {
        "comment_id": "151940166461",
        "parent_comment_id": "",
        "content": "忍者数量增多迟早会开，希望别看到要死了才开。",
        "user_link": "https://tieba.baidu.com/home/main?id=tb.1.bf886a6f.9_aIEcABPllj-3aBKP5thg%3Ft%3D1778148653",
        "user_nickname": "阿栋本栋🐵",
        "user_avatar": "https://gss0.bdstatic.com/6LZ1dD3d1sgCo2Kml5_Y_D3/sys/portrait/item/tb.1.bf886a6f.9_aIEcABPllj-3aBKP5thg?t=1778148653",
        "publish_time": "2025-04-10 18:23:13",
        "ip_location": "北京",
        "sub_comment_count": 1,
        "note_id": "9636099077",
        "note_url": "https://tieba.baidu.com/p/9636099077",
        "tieba_id": "16791220",
        "tieba_name": "火影忍者手游吧",
        "tieba_link": "https://tieba.baidu.com/f?kw=%E7%81%AB%E5%BD%B1%E5%BF%8D%E8%80%85%E6%89%8B%E6%B8%B8",
        "last_modify_ts": 1778148653646
      }
    },
    {
      "id": "tieba_comments_281",
      "platform": "tieba",
      "file_type": "comments",
      "text": "老人不会玩手机也看不懂时间只能看电视了，收视率我只能呵呵了也有确实是喜欢看的有的是没办法才看的",
      "raw_data": {
        "comment_id": "153132865618",
        "parent_comment_id": "",
        "content": "老人不会玩手机也看不懂时间只能看电视了，收视率我只能呵呵了也有确实是喜欢看的有的是没办法才看的",
        "user_link": "https://tieba.baidu.com/home/main?id=tb.1.b4fb0591.5148lmkj7UfqSrJAkBWwTg%3Ft%3D1778148685",
        "user_nickname": "5号实习生",
        "user_avatar": "https://gss0.bdstatic.com/6LZ1dD3d1sgCo2Kml5_Y_D3/sys/portrait/item/tb.1.b4fb0591.5148lmkj7UfqSrJAkBWwTg?t=1778148685",
        "publish_time": "2026-01-26 21:04:44",
        "ip_location": "广东",
        "sub_comment_count": 2,
        "note_id": "10432260972",
        "note_url": "https://tieba.baidu.com/p/10432260972",
        "tieba_id": "9940276",
        "tieba_name": "剧综名场面吧",
        "tieba_link": "https://tieba.baidu.com/f?kw=%E5%89%A7%E7%BB%BC%E5%90%8D%E5%9C%BA%E9%9D%A2",
        "last_modify_ts": 1778148685224
      }
    },
    {
      "id": "tieba_comments_282",
      "platform": "tieba",
      "file_type": "comments",
      "text": "又p假表骗人，如今的yxh号真是传媒毒瘤",
      "raw_data": {
        "comment_id": "153133818516",
        "parent_comment_id": "",
        "content": "又p假表骗人，如今的yxh号真是传媒毒瘤",
        "user_link": "https://tieba.baidu.com/home/main?id=tb.1.ab81ec8b.5iH7ROBOzg9_1kb9oCEmWg%3Ft%3D1778148685",
        "user_nickname": "藏新亦s",
        "user_avatar": "https://gss0.bdstatic.com/6LZ1dD3d1sgCo2Kml5_Y_D3/sys/portrait/item/tb.1.ab81ec8b.5iH7ROBOzg9_1kb9oCEmWg?t=1778148685",
        "publish_time": "2026-01-27 05:09:00",
        "ip_location": "",
        "sub_comment_count": 0,
        "note_id": "10432260972",
        "note_url": "https://tieba.baidu.com/p/10432260972",
        "tieba_id": "9940276",
        "tieba_name": "剧综名场面吧",
        "tieba_link": "https://tieba.baidu.com/f?kw=%E5%89%A7%E7%BB%BC%E5%90%8D%E5%9C%BA%E9%9D%A2",
        "last_modify_ts": 1778148685224
      }
    },
    {
      "id": "tieba_comments_283",
      "platform": "tieba",
      "file_type": "comments",
      "text": "作者总结的今年电视剧央八收视率，感觉很靠谱，很棒shoubai_emoji_face_60shoubai_emoji_face_60shoubai_emoji_face_60应该来自于中国大视听统计的数字，是官方机构具有权威性。至于说到电视机端的观众，都是中老年人，70岁左右的观众，大都受过高等教育，有很高的文化素养，对文娱作品的鉴赏力很强。为中国大视听对国产剧收视率的统计数字的认真严谨精神点赞。",
      "raw_data": {
        "comment_id": "153134022778",
        "parent_comment_id": "",
        "content": "作者总结的今年电视剧央八收视率，感觉很靠谱，很棒shoubai_emoji_face_60shoubai_emoji_face_60shoubai_emoji_face_60应该来自于中国大视听统计的数字，是官方机构具有权威性。至于说到电视机端的观众，都是中老年人，70岁左右的观众，大都受过高等教育，有很高的文化素养，对文娱作品的鉴赏力很强。为中国大视听对国产剧收视率的统计数字的认真严谨精神点赞。",
        "user_link": "https://tieba.baidu.com/home/main?id=tb.1.5a4d5017.fctnflp3lWLO0Zp59PNLgg%3Ft%3D1778148685",
        "user_nickname": "厍白梦w3",
        "user_avatar": "https://gss0.bdstatic.com/6LZ1dD3d1sgCo2Kml5_Y_D3/sys/portrait/item/tb.1.5a4d5017.fctnflp3lWLO0Zp59PNLgg?t=1778148685",
        "publish_time": "2026-01-27 08:17:49",
        "ip_location": "山东",
        "sub_comment_count": 1,
        "note_id": "10432260972",
        "note_url": "https://tieba.baidu.com/p/10432260972",
        "tieba_id": "9940276",
        "tieba_name": "剧综名场面吧",
        "tieba_link": "https://tieba.baidu.com/f?kw=%E5%89%A7%E7%BB%BC%E5%90%8D%E5%9C%BA%E9%9D%A2",
        "last_modify_ts": 1778148685225
      }
    },
    {
      "id": "tieba_comments_284",
      "platform": "tieba",
      "file_type": "comments",
      "text": "小城大事，小城大事都很好看，但是女主的演技还是赵丽颖好过杨幂",
      "raw_data": {
        "comment_id": "153134846145",
        "parent_comment_id": "",
        "content": "小城大事，小城大事都很好看，但是女主的演技还是赵丽颖好过杨幂",
        "user_link": "https://tieba.baidu.com/home/main?id=tb.1.2b1429d6.1G-GFI3LYMW1wBEgzAgfFg%3Ft%3D1778148685",
        "user_nickname": "唔哩阿拉",
        "user_avatar": "https://gss0.bdstatic.com/6LZ1dD3d1sgCo2Kml5_Y_D3/sys/portrait/item/tb.1.2b1429d6.1G-GFI3LYMW1wBEgzAgfFg?t=1778148685",
        "publish_time": "2026-01-27 13:18:10",
        "ip_location": "中国澳门",
        "sub_comment_count": 2,
        "note_id": "10432260972",
        "note_url": "https://tieba.baidu.com/p/10432260972",
        "tieba_id": "9940276",
        "tieba_name": "剧综名场面吧",
        "tieba_link": "https://tieba.baidu.com/f?kw=%E5%89%A7%E7%BB%BC%E5%90%8D%E5%9C%BA%E9%9D%A2",
        "last_modify_ts": 1778148685225
      }
    },
    {
      "id": "tieba_comments_285",
      "platform": "tieba",
      "file_type": "comments",
      "text": "好像没看过几个shoubai_emoji_face_11shoubai_emoji_face_11shoubai_emoji_face_11",
      "raw_data": {
        "comment_id": "153134911362",
        "parent_comment_id": "",
        "content": "好像没看过几个shoubai_emoji_face_11shoubai_emoji_face_11shoubai_emoji_face_11",
        "user_link": "https://tieba.baidu.com/home/main?id=tb.1.d5926af9.wJq1K7aPBoFcZiNlWybCVg%3Ft%3D1778148685",
        "user_nickname": "旅敏学9R",
        "user_avatar": "https://gss0.bdstatic.com/6LZ1dD3d1sgCo2Kml5_Y_D3/sys/portrait/item/tb.1.d5926af9.wJq1K7aPBoFcZiNlWybCVg?t=1778148685",
        "publish_time": "2026-01-27 13:41:56",
        "ip_location": "",
        "sub_comment_count": 0,
        "note_id": "10432260972",
        "note_url": "https://tieba.baidu.com/p/10432260972",
        "tieba_id": "9940276",
        "tieba_name": "剧综名场面吧",
        "tieba_link": "https://tieba.baidu.com/f?kw=%E5%89%A7%E7%BB%BC%E5%90%8D%E5%9C%BA%E9%9D%A2",
        "last_modify_ts": 1778148685225
      }
    },
    {
      "id": "tieba_comments_288",
      "platform": "tieba",
      "file_type": "comments",
      "text": "我没看过呀，下午看小城大事五集连播。",
      "raw_data": {
        "comment_id": "153135583065",
        "parent_comment_id": "",
        "content": "我没看过呀，下午看小城大事五集连播。",
        "user_link": "https://tieba.baidu.com/home/main?id=tb.1.5b530bf6.sVr0EO2q_t33B2enGbX3Vg%3Ft%3D1778148685",
        "user_nickname": "卡卡里一",
        "user_avatar": "https://gss0.bdstatic.com/6LZ1dD3d1sgCo2Kml5_Y_D3/sys/portrait/item/tb.1.5b530bf6.sVr0EO2q_t33B2enGbX3Vg?t=1778148685",
        "publish_time": "2026-01-27 17:37:31",
        "ip_location": "上海",
        "sub_comment_count": 0,
        "note_id": "10432260972",
        "note_url": "https://tieba.baidu.com/p/10432260972",
        "tieba_id": "9940276",
        "tieba_name": "剧综名场面吧",
        "tieba_link": "https://tieba.baidu.com/f?kw=%E5%89%A7%E7%BB%BC%E5%90%8D%E5%9C%BA%E9%9D%A2",
        "last_modify_ts": 1778148685226
      }
    },
    {
      "id": "tieba_comments_289",
      "platform": "tieba",
      "file_type": "comments",
      "text": "除了狂飙，繁花，追风者，其他都没看过，有的连剧名都没听说过",
      "raw_data": {
        "comment_id": "153135922238",
        "parent_comment_id": "",
        "content": "除了狂飙，繁花，追风者，其他都没看过，有的连剧名都没听说过",
        "user_link": "https://tieba.baidu.com/home/main?id=tb.1.bceca2d8.mlk4Bxm5O9v02KWbkzHyig%3Ft%3D1778148685",
        "user_nickname": "派蒙拼盘39",
        "user_avatar": "https://gss0.bdstatic.com/6LZ1dD3d1sgCo2Kml5_Y_D3/sys/portrait/item/tb.1.bceca2d8.mlk4Bxm5O9v02KWbkzHyig?t=1778148685",
        "publish_time": "2026-01-27 19:39:49",
        "ip_location": "",
        "sub_comment_count": 0,
        "note_id": "10432260972",
        "note_url": "https://tieba.baidu.com/p/10432260972",
        "tieba_id": "9940276",
        "tieba_name": "剧综名场面吧",
        "tieba_link": "https://tieba.baidu.com/f?kw=%E5%89%A7%E7%BB%BC%E5%90%8D%E5%9C%BA%E9%9D%A2",
        "last_modify_ts": 1778148685226
      }
    },
    {
      "id": "tieba_comments_291",
      "platform": "tieba",
      "file_type": "comments",
      "text": "至戒靠德，一定要积德行善，做到正己化人，把玩手机，看小说的时间分一部分出来帮助戒友才是正解。",
      "raw_data": {
        "comment_id": "153479297300",
        "parent_comment_id": "",
        "content": "至戒靠德，一定要积德行善，做到正己化人，把玩手机，看小说的时间分一部分出来帮助戒友才是正解。",
        "user_link": "https://tieba.baidu.com/home/main?id=tb.1.62962b60.qkZ8XNen821qkH_lx5XmqQ%3Ft%3D1778148689",
        "user_nickname": "戒者海泉🍀",
        "user_avatar": "https://gss0.bdstatic.com/6LZ1dD3d1sgCo2Kml5_Y_D3/sys/portrait/item/tb.1.62962b60.qkZ8XNen821qkH_lx5XmqQ?t=1778148689",
        "publish_time": "2026-05-03 10:54:53",
        "ip_location": "湖南",
        "sub_comment_count": 0,
        "note_id": "10686424813",
        "note_url": "https://tieba.baidu.com/p/10686424813",
        "tieba_id": "401299",
        "tieba_name": "戒色吧",
        "tieba_link": "https://tieba.baidu.com/f?kw=%E6%88%92%E8%89%B2",
        "last_modify_ts": 1778148689533
      }
    },
    {
      "id": "tieba_comments_292",
      "platform": "tieba",
      "file_type": "comments",
      "text": "经常SY的人，会导致注意力下降，集中力下降，智力下降，影响学业和工作，因为肾上通于脑。经常SY的人，会导致雄性激素增多，内分泌失调，就容易长痘，长痤疮，很影响一个人的心情和自信。经常SY的人，会导致脱发，发为肾之华，脱发就很影响外在形象，对个人自信心也会受到很大打击，也会显老。经常SY的人，会耳鸣耳聋，因为肾开窍于耳。经常SY的人，会导致腰酸背痛，因为腰为肾之府。经常SY的人，会腿软，因为肾主骨。经常SY的人，会导致前列腺炎充血，会尿急尿频尿不尽，会YWZX，YWZX很影响男性自尊心，不敢找对象，不敢结婚。 经常SY的人，就会胆小自卑懦落，因为肾主恐。经常SY的人，就会急躁易怒，因为肝肾同源，肝不好，就容易生气。身体不健康，就会影响身心也不健康，人会变得敏感脆弱，严重的话就会有焦虑症，神经症，痛不欲生，生不如死。 经常SY的人，生理上已经百病丛生，心理上已经痛不欲生，在职场上怎么可能还有建树，在爱情上怎么还敢追求对象，在家庭上怎么敢承担重任，在钱财上怎么可能还会有福报。能够苟延残喘，就已经是不错了。 经常SY的人，怎么自救呢？就是要及时醒悟过来，认清邪SY的危害，赶紧戒除。症状严重的话",
      "raw_data": {
        "comment_id": "153480947447",
        "parent_comment_id": "",
        "content": "经常SY的人，会导致注意力下降，集中力下降，智力下降，影响学业和工作，因为肾上通于脑。经常SY的人，会导致雄性激素增多，内分泌失调，就容易长痘，长痤疮，很影响一个人的心情和自信。经常SY的人，会导致脱发，发为肾之华，脱发就很影响外在形象，对个人自信心也会受到很大打击，也会显老。经常SY的人，会耳鸣耳聋，因为肾开窍于耳。经常SY的人，会导致腰酸背痛，因为腰为肾之府。经常SY的人，会腿软，因为肾主骨。经常SY的人，会导致前列腺炎充血，会尿急尿频尿不尽，会YWZX，YWZX很影响男性自尊心，不敢找对象，不敢结婚。 经常SY的人，就会胆小自卑懦落，因为肾主恐。经常SY的人，就会急躁易怒，因为肝肾同源，肝不好，就容易生气。身体不健康，就会影响身心也不健康，人会变得敏感脆弱，严重的话就会有焦虑症，神经症，痛不欲生，生不如死。 经常SY的人，生理上已经百病丛生，心理上已经痛不欲生，在职场上怎么可能还有建树，在爱情上怎么还敢追求对象，在家庭上怎么敢承担重任，在钱财上怎么可能还会有福报。能够苟延残喘，就已经是不错了。 经常SY的人，怎么自救呢？就是要及时醒悟过来，认清邪SY的危害，赶紧戒除。症状严重的话，赶紧去三甲医院或者中医院看好的中医，积极配合调理。多行善，行善化解欲望，行善积德，行善提升阳气，可以帮助父母做事，帮助吧友答疑，公交车让座等等，至少日行一善。早睡早起多运动。不YY，YY是暗漏，不控制住很难恢复。还有一些养生办法，八段锦，站桩，食补都可以配合恢复。在这里非常感谢飞翔师兄的戒为良药，他让我们认清SY的危害，也教我们恢复的办法，是一本很系统，很专业的戒色书籍。大家可以去认真学习戒为良药，提高自己的觉悟和保持警惕，对戒色养生有很大帮助。",
        "user_link": "https://tieba.baidu.com/home/main?id=tb.1.a6efe9db.pJRXyuAIADrU7hXTojX04Q%3Ft%3D1778148689",
        "user_nickname": "w1573910053",
        "user_avatar": "https://gss0.bdstatic.com/6LZ1dD3d1sgCo2Kml5_Y_D3/sys/portrait/item/tb.1.a6efe9db.pJRXyuAIADrU7hXTojX04Q?t=1778148689",
        "publish_time": "2026-05-03 21:46:34",
        "ip_location": "福建",
        "sub_comment_count": 0,
        "note_id": "10686424813",
        "note_url": "https://tieba.baidu.com/p/10686424813",
        "tieba_id": "401299",
        "tieba_name": "戒色吧",
        "tieba_link": "https://tieba.baidu.com/f?kw=%E6%88%92%E8%89%B2",
        "last_modify_ts": 1778148689534
      }
    },
    {
      "id": "tieba_comments_294",
      "platform": "tieba",
      "file_type": "comments",
      "text": "加油戒色 多看戒色文章 吸取教训",
      "raw_data": {
        "comment_id": "153480362163",
        "parent_comment_id": "",
        "content": "加油戒色 多看戒色文章 吸取教训",
        "user_link": "https://tieba.baidu.com/home/main?id=tb.1.429275b1.QCzIAiz-AFhPfXQUsdhXdw%3Ft%3D1778148689",
        "user_nickname": "一个人的坚持会有多难",
        "user_avatar": "https://gss0.bdstatic.com/6LZ1dD3d1sgCo2Kml5_Y_D3/sys/portrait/item/tb.1.429275b1.QCzIAiz-AFhPfXQUsdhXdw?t=1778148689",
        "publish_time": "2026-05-03 18:08:22",
        "ip_location": "河南",
        "sub_comment_count": 0,
        "note_id": "10686424813",
        "note_url": "https://tieba.baidu.com/p/10686424813",
        "tieba_id": "401299",
        "tieba_name": "戒色吧",
        "tieba_link": "https://tieba.baidu.com/f?kw=%E6%88%92%E8%89%B2",
        "last_modify_ts": 1778148689535
      }
    },
    {
      "id": "tieba_comments_295",
      "platform": "tieba",
      "file_type": "comments",
      "text": "加油，曾国藩说过，败人俩字，非傲即惰。一旦放松对戒色文章的学习，很快就会破戒，人与人最大的差距就在于坚持，成功就在于坚持坚持再坚持。",
      "raw_data": {
        "comment_id": "153480357498",
        "parent_comment_id": "",
        "content": "加油，曾国藩说过，败人俩字，非傲即惰。一旦放松对戒色文章的学习，很快就会破戒，人与人最大的差距就在于坚持，成功就在于坚持坚持再坚持。",
        "user_link": "https://tieba.baidu.com/home/main?id=tb.1.90f2d6be.5BHrHvhMOFGH9ahoPkGtMQ%3Ft%3D1778148689",
        "user_nickname": "mjjtttttt",
        "user_avatar": "https://gss0.bdstatic.com/6LZ1dD3d1sgCo2Kml5_Y_D3/sys/portrait/item/tb.1.90f2d6be.5BHrHvhMOFGH9ahoPkGtMQ?t=1778148689",
        "publish_time": "2026-05-03 18:06:20",
        "ip_location": "辽宁",
        "sub_comment_count": 0,
        "note_id": "10686424813",
        "note_url": "https://tieba.baidu.com/p/10686424813",
        "tieba_id": "401299",
        "tieba_name": "戒色吧",
        "tieba_link": "https://tieba.baidu.com/f?kw=%E6%88%92%E8%89%B2",
        "last_modify_ts": 1778148689535
      }
    },
    {
      "id": "tieba_comments_296",
      "platform": "tieba",
      "file_type": "comments",
      "text": "赶紧戒掉加强学习。多学习戒炉知识，看看了凡四训，寿康宝鉴，多学习传统文化积累福德智慧获得正能量更容易成功，推荐几个微信公众号关注学习，湖心亭看雪客，天悦名坊，大愿小跟班，",
      "raw_data": {
        "comment_id": "153480321532",
        "parent_comment_id": "",
        "content": "赶紧戒掉加强学习。多学习戒炉知识，看看了凡四训，寿康宝鉴，多学习传统文化积累福德智慧获得正能量更容易成功，推荐几个微信公众号关注学习，湖心亭看雪客，天悦名坊，大愿小跟班，",
        "user_link": "https://tieba.baidu.com/home/main?id=tb.1.9d4b5262.NfU9B92oizr7s-ZwKWYXBA%3Ft%3D1778148689",
        "user_nickname": "首楞严三昧🍭",
        "user_avatar": "https://gss0.bdstatic.com/6LZ1dD3d1sgCo2Kml5_Y_D3/sys/portrait/item/tb.1.9d4b5262.NfU9B92oizr7s-ZwKWYXBA?t=1778148689",
        "publish_time": "2026-05-03 17:51:18",
        "ip_location": "黑龙江",
        "sub_comment_count": 0,
        "note_id": "10686424813",
        "note_url": "https://tieba.baidu.com/p/10686424813",
        "tieba_id": "401299",
        "tieba_name": "戒色吧",
        "tieba_link": "https://tieba.baidu.com/f?kw=%E6%88%92%E8%89%B2",
        "last_modify_ts": 1778148689535
      }
    },
    {
      "id": "tieba_comments_297",
      "platform": "tieba",
      "file_type": "comments",
      "text": "神经症的本质是阴阳失衡了，比如阳盛阴衰，晚上阳不入阴，人就会过度亢奋，翻来覆去睡不着觉。要调节神经症，首先睡好子午觉，作息规律远远不够，有的人每天凌晨1点睡早上6点起这也很规律，但对身体伤害却很大。建议每天11点前必须上床，中午11点后小憩20分钟。另外跑步的话可以减少频率，长期sy的人身体往往比较虚，过度有氧反而耗费气血，加重神经衰弱。最后希望楼主放平心态吧，以一个人过来人的身份讲，高考这种考试能到什么程度，从你出生那刻起，大运和流年基本上给你定了，努力只是决定你触及区间的上限还是下限。成绩理想固然可喜可贺，不理想也不必苛责自己，人生路还很长，18岁的你在未来还有无限可能，加油吧。",
      "raw_data": {
        "comment_id": "153480006798",
        "parent_comment_id": "",
        "content": "神经症的本质是阴阳失衡了，比如阳盛阴衰，晚上阳不入阴，人就会过度亢奋，翻来覆去睡不着觉。要调节神经症，首先睡好子午觉，作息规律远远不够，有的人每天凌晨1点睡早上6点起这也很规律，但对身体伤害却很大。建议每天11点前必须上床，中午11点后小憩20分钟。另外跑步的话可以减少频率，长期sy的人身体往往比较虚，过度有氧反而耗费气血，加重神经衰弱。最后希望楼主放平心态吧，以一个人过来人的身份讲，高考这种考试能到什么程度，从你出生那刻起，大运和流年基本上给你定了，努力只是决定你触及区间的上限还是下限。成绩理想固然可喜可贺，不理想也不必苛责自己，人生路还很长，18岁的你在未来还有无限可能，加油吧。",
        "user_link": "https://tieba.baidu.com/home/main?id=tb.1.f4805ac.PT5V4u25Qq-NoPZZbEbujA%3Ft%3D1778148689",
        "user_nickname": "6ackPack",
        "user_avatar": "https://gss0.bdstatic.com/6LZ1dD3d1sgCo2Kml5_Y_D3/sys/portrait/item/tb.1.f4805ac.PT5V4u25Qq-NoPZZbEbujA?t=1778148689",
        "publish_time": "2026-05-03 15:43:11",
        "ip_location": "江西",
        "sub_comment_count": 0,
        "note_id": "10686424813",
        "note_url": "https://tieba.baidu.com/p/10686424813",
        "tieba_id": "401299",
        "tieba_name": "戒色吧",
        "tieba_link": "https://tieba.baidu.com/f?kw=%E6%88%92%E8%89%B2",
        "last_modify_ts": 1778148689536
      }
    },
    {
      "id": "tieba_comments_298",
      "platform": "tieba",
      "file_type": "comments",
      "text": "xy严重时有可能出现牙痛头痛、刷牙出血、烂牙",
      "raw_data": {
        "comment_id": "153479707267",
        "parent_comment_id": "",
        "content": "xy严重时有可能出现牙痛头痛、刷牙出血、烂牙",
        "user_link": "https://tieba.baidu.com/home/main?id=tb.1.390ad5aa.SXqweCVwkdr6A6-g7hHgPA%3Ft%3D1778148689",
        "user_nickname": "贴吧用户_G39NKVJ",
        "user_avatar": "https://gss0.bdstatic.com/6LZ1dD3d1sgCo2Kml5_Y_D3/sys/portrait/item/tb.1.390ad5aa.SXqweCVwkdr6A6-g7hHgPA?t=1778148689",
        "publish_time": "2026-05-03 13:40:22",
        "ip_location": "海南",
        "sub_comment_count": 0,
        "note_id": "10686424813",
        "note_url": "https://tieba.baidu.com/p/10686424813",
        "tieba_id": "401299",
        "tieba_name": "戒色吧",
        "tieba_link": "https://tieba.baidu.com/f?kw=%E6%88%92%E8%89%B2",
        "last_modify_ts": 1778148689536
      }
    },
    {
      "id": "tieba_comments_299",
      "platform": "tieba",
      "file_type": "comments",
      "text": "楼主加油！经常邪淫，会导致脑袋骨髓空洞，记忆力思维能力下降，丢三落四，做事经常出错，学习能力下降。女色本来就是不净的，薄皮之下骨肉脓血，屎尿毛发，秽臭不堪，有什么值得贪恋的？一定要戒除邪淫，不然贫贱一生！我戒了321天了，我的戒色方法你可以参考一下：第一，多看看戒为良药，好的语句可以记下来或者手机截图，平时多复习自己喜欢的语句截图或笔记，你的感悟会越来越深。第二，要远离黄源，千万不要看黄，黄片是最毒的东西，掏空你的脑髓骨髓，消磨你的志气，腐蚀你的灵魂，开发你的兽性，让你变成一滩烂泥，所有不良资源和网站都要删除！第三，要做好情绪管理，大喜大悲都要控制自己，用断念口诀断除邪念，绝对不能被心魔怂恿，记住不破戒是底线，破戒了就是噩梦和地狱，你可能几年都爬不出来，对你的身体和运势会造成很坏的影响！第四，每天抽出半小时练习断念口诀，把断念能力提升上来，发现念头跑了的那一刻拉回就是断念，断念的次数越多，你就会越精进，邪念袭脑就能轻松断掉。第五，平时要少玩手机，千万不要沉迷短视频，会让你的戒色意识弱化的，而且网上有很多擦边视频图片，很容易导致破戒。第六，可以每天看点不净观白骨观视频破除对女色的贪恋，没",
      "raw_data": {
        "comment_id": "153479563833",
        "parent_comment_id": "",
        "content": "楼主加油！经常邪淫，会导致脑袋骨髓空洞，记忆力思维能力下降，丢三落四，做事经常出错，学习能力下降。女色本来就是不净的，薄皮之下骨肉脓血，屎尿毛发，秽臭不堪，有什么值得贪恋的？一定要戒除邪淫，不然贫贱一生！我戒了321天了，我的戒色方法你可以参考一下：第一，多看看戒为良药，好的语句可以记下来或者手机截图，平时多复习自己喜欢的语句截图或笔记，你的感悟会越来越深。第二，要远离黄源，千万不要看黄，黄片是最毒的东西，掏空你的脑髓骨髓，消磨你的志气，腐蚀你的灵魂，开发你的兽性，让你变成一滩烂泥，所有不良资源和网站都要删除！第三，要做好情绪管理，大喜大悲都要控制自己，用断念口诀断除邪念，绝对不能被心魔怂恿，记住不破戒是底线，破戒了就是噩梦和地狱，你可能几年都爬不出来，对你的身体和运势会造成很坏的影响！第四，每天抽出半小时练习断念口诀，把断念能力提升上来，发现念头跑了的那一刻拉回就是断念，断念的次数越多，你就会越精进，邪念袭脑就能轻松断掉。第五，平时要少玩手机，千万不要沉迷短视频，会让你的戒色意识弱化的，而且网上有很多擦边视频图片，很容易导致破戒。第六，可以每天看点不净观白骨观视频破除对女色的贪恋，没事多用喜马拉雅软件听听戒色音频。第七，每天早晚一定要抽出时间锻炼，可以是散步，跑步等，形成习惯你的执行力就变强了，精力体力会不断恢复，反过来对你戒色也有帮助，我每天早上快走一小时，晚饭后散步半小时以上，精力和执行力有了很大提升，做戒色日课就更简单。第八，要学习传统文化，可以看看寿康宝鉴、欲海回狂、弟子规、了凡四训等道德善书，培养你的浩然正气。第九，要孝敬父母，不要惹父母生气，多多关心他们，他们是我们的根，父母真的老了，需要你承担起为人子女的责任，再不能邪淫让父母担惊受怕了。第十，多来戒色吧帮助吧友，我每天早中晚共鼓励100位吧友戒色，把你看过的精品贴以及案例后的心得体会反过来鼓励吧友，帮他们解决问题，这也会加深你对戒邪淫的理解，其他戒友如果戒色成功以及劝诫他人戒色，所产生的功德也有你的一部分。我就是靠着这个方法戒到现在，一起加油！",
        "user_link": "https://tieba.baidu.com/home/main?id=tb.1.a352a999.s6A3oG3AhIZF3xyvO4XLUg%3Ft%3D1778148689",
        "user_nickname": "贴吧用户_aZNaQtX",
        "user_avatar": "https://gss0.bdstatic.com/6LZ1dD3d1sgCo2Kml5_Y_D3/sys/portrait/item/tb.1.a352a999.s6A3oG3AhIZF3xyvO4XLUg?t=1778148689",
        "publish_time": "2026-05-03 12:42:46",
        "ip_location": "江西",
        "sub_comment_count": 0,
        "note_id": "10686424813",
        "note_url": "https://tieba.baidu.com/p/10686424813",
        "tieba_id": "401299",
        "tieba_name": "戒色吧",
        "tieba_link": "https://tieba.baidu.com/f?kw=%E6%88%92%E8%89%B2",
        "last_modify_ts": 1778148689536
      }
    },
    {
      "id": "tieba_comments_300",
      "platform": "tieba",
      "file_type": "comments",
      "text": "想要戒掉一定要多学习戒为良药，以戒为师，强戒必破",
      "raw_data": {
        "comment_id": "153479421250",
        "parent_comment_id": "",
        "content": "想要戒掉一定要多学习戒为良药，以戒为师，强戒必破",
        "user_link": "https://tieba.baidu.com/home/main?id=tb.1.de1e6455.Wg9Yge-Nvr5Gz_x4b9mA3g%3Ft%3D1778148689",
        "user_nickname": "◎💢🌀c",
        "user_avatar": "https://gss0.bdstatic.com/6LZ1dD3d1sgCo2Kml5_Y_D3/sys/portrait/item/tb.1.de1e6455.Wg9Yge-Nvr5Gz_x4b9mA3g?t=1778148689",
        "publish_time": "2026-05-03 11:44:48",
        "ip_location": "福建",
        "sub_comment_count": 0,
        "note_id": "10686424813",
        "note_url": "https://tieba.baidu.com/p/10686424813",
        "tieba_id": "401299",
        "tieba_name": "戒色吧",
        "tieba_link": "https://tieba.baidu.com/f?kw=%E6%88%92%E8%89%B2",
        "last_modify_ts": 1778148689536
      }
    },
    {
      "id": "tieba_comments_302",
      "platform": "tieba",
      "file_type": "comments",
      "text": "《直接找开发者请教》这有点超纲吧（",
      "raw_data": {
        "comment_id": "153218023792",
        "parent_comment_id": "",
        "content": "《直接找开发者请教》这有点超纲吧（",
        "user_link": "https://tieba.baidu.com/home/main?id=tb.1.5c180c68.tc6wZC8JhLTjh-Gmfay5Hw%3Ft%3D1778148693",
        "user_nickname": "tebness",
        "user_avatar": "https://gss0.bdstatic.com/6LZ1dD3d1sgCo2Kml5_Y_D3/sys/portrait/item/tb.1.5c180c68.tc6wZC8JhLTjh-Gmfay5Hw?t=1778148693",
        "publish_time": "2026-02-20 04:43:50",
        "ip_location": "陕西",
        "sub_comment_count": 0,
        "note_id": "10500049873",
        "note_url": "https://tieba.baidu.com/p/10500049873",
        "tieba_id": "707597",
        "tieba_name": "steam吧",
        "tieba_link": "https://tieba.baidu.com/f?kw=steam",
        "last_modify_ts": 1778148693701
      }
    },
    {
      "id": "tieba_comments_303",
      "platform": "tieba",
      "file_type": "comments",
      "text": "思考，行动，并解决问题一直都是最有成就感的事情之一，很多时候游戏也只是简化了这个循环来让玩家获得类似的愉悦。",
      "raw_data": {
        "comment_id": "153218140450",
        "parent_comment_id": "",
        "content": "思考，行动，并解决问题一直都是最有成就感的事情之一，很多时候游戏也只是简化了这个循环来让玩家获得类似的愉悦。",
        "user_link": "https://tieba.baidu.com/home/main?id=tb.1.9478b445.5C3o1OnoV_4jJT8SwErSSA%3Ft%3D1778148693",
        "user_nickname": "Laurence♝",
        "user_avatar": "https://gss0.bdstatic.com/6LZ1dD3d1sgCo2Kml5_Y_D3/sys/portrait/item/tb.1.9478b445.5C3o1OnoV_4jJT8SwErSSA?t=1778148693",
        "publish_time": "2026-02-20 07:32:37",
        "ip_location": "上海",
        "sub_comment_count": 0,
        "note_id": "10500049873",
        "note_url": "https://tieba.baidu.com/p/10500049873",
        "tieba_id": "707597",
        "tieba_name": "steam吧",
        "tieba_link": "https://tieba.baidu.com/f?kw=steam",
        "last_modify_ts": 1778148693701
      }
    },
    {
      "id": "tieba_comments_304",
      "platform": "tieba",
      "file_type": "comments",
      "text": "有探索精神和独立解决问题的想法是好的 但还是不明白给图片转个格式是怎么能花六个小时然后还要写几百字小作文来庆祝一下的",
      "raw_data": {
        "comment_id": "153218149341",
        "parent_comment_id": "",
        "content": "有探索精神和独立解决问题的想法是好的 但还是不明白给图片转个格式是怎么能花六个小时然后还要写几百字小作文来庆祝一下的",
        "user_link": "https://tieba.baidu.com/home/main?id=tb.1.59be5963.7nfGBhN5HPVjzY5oB1sCDQ%3Ft%3D1778148693",
        "user_nickname": "dseee",
        "user_avatar": "https://gss0.bdstatic.com/6LZ1dD3d1sgCo2Kml5_Y_D3/sys/portrait/item/tb.1.59be5963.7nfGBhN5HPVjzY5oB1sCDQ?t=1778148693",
        "publish_time": "2026-02-20 07:39:54",
        "ip_location": "天津",
        "sub_comment_count": 1,
        "note_id": "10500049873",
        "note_url": "https://tieba.baidu.com/p/10500049873",
        "tieba_id": "707597",
        "tieba_name": "steam吧",
        "tieba_link": "https://tieba.baidu.com/f?kw=steam",
        "last_modify_ts": 1778148693702
      }
    },
    {
      "id": "tieba_comments_305",
      "platform": "tieba",
      "file_type": "comments",
      "text": "同遇到过这种问题，虽然有这份研究的心是好的，但这东西b站上就有教程",
      "raw_data": {
        "comment_id": "153218303144",
        "parent_comment_id": "",
        "content": "同遇到过这种问题，虽然有这份研究的心是好的，但这东西b站上就有教程",
        "user_link": "https://tieba.baidu.com/home/main?id=tb.1.9e9276a9.HXeBVraaIie78oM3MHIj2w%3Ft%3D1778148693",
        "user_nickname": "КЁRtaur",
        "user_avatar": "https://gss0.bdstatic.com/6LZ1dD3d1sgCo2Kml5_Y_D3/sys/portrait/item/tb.1.9e9276a9.HXeBVraaIie78oM3MHIj2w?t=1778148693",
        "publish_time": "2026-02-20 09:09:16",
        "ip_location": "广西",
        "sub_comment_count": 0,
        "note_id": "10500049873",
        "note_url": "https://tieba.baidu.com/p/10500049873",
        "tieba_id": "707597",
        "tieba_name": "steam吧",
        "tieba_link": "https://tieba.baidu.com/f?kw=steam",
        "last_modify_ts": 1778148693702
      }
    },
    {
      "id": "tieba_comments_306",
      "platform": "tieba",
      "file_type": "comments",
      "text": "我在看完前都没有想到你居然改个拓展名就扔进去了",
      "raw_data": {
        "comment_id": "153218435477",
        "parent_comment_id": "",
        "content": "我在看完前都没有想到你居然改个拓展名就扔进去了",
        "user_link": "https://tieba.baidu.com/home/main?id=tb.1.36607613.8W9-Or1-tCXhTUa78YVwMg%3Ft%3D1778148693",
        "user_nickname": "贴吧用户_0bCa1UP",
        "user_avatar": "https://gss0.bdstatic.com/6LZ1dD3d1sgCo2Kml5_Y_D3/sys/portrait/item/tb.1.36607613.8W9-Or1-tCXhTUa78YVwMg?t=1778148693",
        "publish_time": "2026-02-20 10:07:05",
        "ip_location": "浙江",
        "sub_comment_count": 0,
        "note_id": "10500049873",
        "note_url": "https://tieba.baidu.com/p/10500049873",
        "tieba_id": "707597",
        "tieba_name": "steam吧",
        "tieba_link": "https://tieba.baidu.com/f?kw=steam",
        "last_modify_ts": 1778148693702
      }
    },
    {
      "id": "tieba_comments_307",
      "platform": "tieba",
      "file_type": "comments",
      "text": "这么强image_emoticon71",
      "raw_data": {
        "comment_id": "153218679811",
        "parent_comment_id": "",
        "content": "这么强image_emoticon71",
        "user_link": "https://tieba.baidu.com/home/main?id=tb.1.7279da82.S8M5ImwWK4GV-HQ1bFMa7w%3Ft%3D1778148693",
        "user_nickname": "贴吧用户_GySMZDS",
        "user_avatar": "https://gss0.bdstatic.com/6LZ1dD3d1sgCo2Kml5_Y_D3/sys/portrait/item/tb.1.7279da82.S8M5ImwWK4GV-HQ1bFMa7w?t=1778148693",
        "publish_time": "2026-02-20 11:44:01",
        "ip_location": "湖北",
        "sub_comment_count": 0,
        "note_id": "10500049873",
        "note_url": "https://tieba.baidu.com/p/10500049873",
        "tieba_id": "707597",
        "tieba_name": "steam吧",
        "tieba_link": "https://tieba.baidu.com/f?kw=steam",
        "last_modify_ts": 1778148693702
      }
    },
    {
      "id": "tieba_comments_308",
      "platform": "tieba",
      "file_type": "comments",
      "text": "image_emoticon13",
      "raw_data": {
        "comment_id": "153218993017",
        "parent_comment_id": "",
        "content": "image_emoticon13",
        "user_link": "https://tieba.baidu.com/home/main?id=tb.1.e909fa01.IskqoW4MPtns7Rb9-lZE-g%3Ft%3D1778148693",
        "user_nickname": "mole0Lisa",
        "user_avatar": "https://gss0.bdstatic.com/6LZ1dD3d1sgCo2Kml5_Y_D3/sys/portrait/item/tb.1.e909fa01.IskqoW4MPtns7Rb9-lZE-g?t=1778148693",
        "publish_time": "2026-02-20 13:46:00",
        "ip_location": "山东",
        "sub_comment_count": 0,
        "note_id": "10500049873",
        "note_url": "https://tieba.baidu.com/p/10500049873",
        "tieba_id": "707597",
        "tieba_name": "steam吧",
        "tieba_link": "https://tieba.baidu.com/f?kw=steam",
        "last_modify_ts": 1778148693703
      }
    },
    {
      "id": "tieba_comments_309",
      "platform": "tieba",
      "file_type": "comments",
      "text": "我也用8p，不玩游戏，日常使用没啥问题！",
      "raw_data": {
        "comment_id": "153431720199",
        "parent_comment_id": "",
        "content": "我也用8p，不玩游戏，日常使用没啥问题！",
        "user_link": "https://tieba.baidu.com/home/main?id=tb.1.7e7e4894.NCBL35gK7-c5wEXn9QgTUw%3Ft%3D1778148697",
        "user_nickname": "风呤云",
        "user_avatar": "https://gss0.bdstatic.com/6LZ1dD3d1sgCo2Kml5_Y_D3/sys/portrait/item/tb.1.7e7e4894.NCBL35gK7-c5wEXn9QgTUw?t=1778148697",
        "publish_time": "2026-04-18 20:08:53",
        "ip_location": "广东",
        "sub_comment_count": 0,
        "note_id": "10649112811",
        "note_url": "https://tieba.baidu.com/p/10649112811",
        "tieba_id": "26491947",
        "tieba_name": "关注屏幕健康吧",
        "tieba_link": "https://tieba.baidu.com/f?kw=%E5%85%B3%E6%B3%A8%E5%B1%8F%E5%B9%95%E5%81%A5%E5%BA%B7",
        "last_modify_ts": 1778148697943
      }
    },
    {
      "id": "tieba_comments_310",
      "platform": "tieba",
      "file_type": "comments",
      "text": "实在不行，双持吧，回家用小平板",
      "raw_data": {
        "comment_id": "153430797766",
        "parent_comment_id": "",
        "content": "实在不行，双持吧，回家用小平板",
        "user_link": "https://tieba.baidu.com/home/main?id=tb.1.d097602f.g4F27oCsTashyZWv_heFbw%3Ft%3D1778148697",
        "user_nickname": "dazhao2",
        "user_avatar": "https://gss0.bdstatic.com/6LZ1dD3d1sgCo2Kml5_Y_D3/sys/portrait/item/tb.1.d097602f.g4F27oCsTashyZWv_heFbw?t=1778148697",
        "publish_time": "2026-04-18 14:29:28",
        "ip_location": "重庆",
        "sub_comment_count": 1,
        "note_id": "10649112811",
        "note_url": "https://tieba.baidu.com/p/10649112811",
        "tieba_id": "26491947",
        "tieba_name": "关注屏幕健康吧",
        "tieba_link": "https://tieba.baidu.com/f?kw=%E5%85%B3%E6%B3%A8%E5%B1%8F%E5%B9%95%E5%81%A5%E5%BA%B7",
        "last_modify_ts": 1778148697943
      }
    },
    {
      "id": "tieba_comments_311",
      "platform": "tieba",
      "file_type": "comments",
      "text": "v30pro 运存价到12g",
      "raw_data": {
        "comment_id": "153479098398",
        "parent_comment_id": "",
        "content": "v30pro 运存价到12g",
        "user_link": "https://tieba.baidu.com/home/main?id=tb.1.fb5210a7.J7ET0fv0YZe5-cKh0IBXhg%3Ft%3D1778148697",
        "user_nickname": "超的boss",
        "user_avatar": "https://gss0.bdstatic.com/6LZ1dD3d1sgCo2Kml5_Y_D3/sys/portrait/item/tb.1.fb5210a7.J7ET0fv0YZe5-cKh0IBXhg?t=1778148697",
        "publish_time": "2026-05-03 09:29:10",
        "ip_location": "广东",
        "sub_comment_count": 0,
        "note_id": "10649112811",
        "note_url": "https://tieba.baidu.com/p/10649112811",
        "tieba_id": "26491947",
        "tieba_name": "关注屏幕健康吧",
        "tieba_link": "https://tieba.baidu.com/f?kw=%E5%85%B3%E6%B3%A8%E5%B1%8F%E5%B9%95%E5%81%A5%E5%BA%B7",
        "last_modify_ts": 1778148697943
      }
    },
    {
      "id": "tieba_comments_312",
      "platform": "tieba",
      "file_type": "comments",
      "text": "这不得改个全反射屏幕image_emoticon67",
      "raw_data": {
        "comment_id": "153431318886",
        "parent_comment_id": "",
        "content": "这不得改个全反射屏幕image_emoticon67",
        "user_link": "https://tieba.baidu.com/home/main?id=tb.1.6ceb4842.j2OYunich0AvT19JxZRZFw%3Ft%3D1778148697",
        "user_nickname": "许愿半夜",
        "user_avatar": "https://gss0.bdstatic.com/6LZ1dD3d1sgCo2Kml5_Y_D3/sys/portrait/item/tb.1.6ceb4842.j2OYunich0AvT19JxZRZFw?t=1778148697",
        "publish_time": "2026-04-18 17:41:38",
        "ip_location": "广东",
        "sub_comment_count": 0,
        "note_id": "10649112811",
        "note_url": "https://tieba.baidu.com/p/10649112811",
        "tieba_id": "26491947",
        "tieba_name": "关注屏幕健康吧",
        "tieba_link": "https://tieba.baidu.com/f?kw=%E5%85%B3%E6%B3%A8%E5%B1%8F%E5%B9%95%E5%81%A5%E5%BA%B7",
        "last_modify_ts": 1778148697944
      }
    },
    {
      "id": "tieba_comments_313",
      "platform": "tieba",
      "file_type": "comments",
      "text": "用tcl70pto试试，合适记得回来发红包",
      "raw_data": {
        "comment_id": "153430931714",
        "parent_comment_id": "",
        "content": "用tcl70pto试试，合适记得回来发红包",
        "user_link": "https://tieba.baidu.com/home/main?id=tb.1.fbd65956.9ClsDvG6hpsPftoJhqzwoQ%3Ft%3D1778148697",
        "user_nickname": "贴吧用户_5GEXX92",
        "user_avatar": "https://gss0.bdstatic.com/6LZ1dD3d1sgCo2Kml5_Y_D3/sys/portrait/item/tb.1.fbd65956.9ClsDvG6hpsPftoJhqzwoQ?t=1778148697",
        "publish_time": "2026-04-18 15:19:55",
        "ip_location": "湖北",
        "sub_comment_count": 0,
        "note_id": "10649112811",
        "note_url": "https://tieba.baidu.com/p/10649112811",
        "tieba_id": "26491947",
        "tieba_name": "关注屏幕健康吧",
        "tieba_link": "https://tieba.baidu.com/f?kw=%E5%85%B3%E6%B3%A8%E5%B1%8F%E5%B9%95%E5%81%A5%E5%BA%B7",
        "last_modify_ts": 1778148697944
      }
    },
    {
      "id": "tieba_comments_315",
      "platform": "tieba",
      "file_type": "comments",
      "text": "Z11X和G100和畅享90 流畅度高的就是Z11X了 不过打游戏流畅就别想了",
      "raw_data": {
        "comment_id": "153431341711",
        "parent_comment_id": "",
        "content": "Z11X和G100和畅享90 流畅度高的就是Z11X了 不过打游戏流畅就别想了",
        "user_link": "https://tieba.baidu.com/home/main?id=tb.1.247da2aa.iQyHEl0ZZxZtTZUI4JbiHQ%3Ft%3D1778148697",
        "user_nickname": "77236045",
        "user_avatar": "https://gss0.bdstatic.com/6LZ1dD3d1sgCo2Kml5_Y_D3/sys/portrait/item/tb.1.247da2aa.iQyHEl0ZZxZtTZUI4JbiHQ?t=1778148697",
        "publish_time": "2026-04-18 17:50:25",
        "ip_location": "河南",
        "sub_comment_count": 0,
        "note_id": "10649112811",
        "note_url": "https://tieba.baidu.com/p/10649112811",
        "tieba_id": "26491947",
        "tieba_name": "关注屏幕健康吧",
        "tieba_link": "https://tieba.baidu.com/f?kw=%E5%85%B3%E6%B3%A8%E5%B1%8F%E5%B9%95%E5%81%A5%E5%BA%B7",
        "last_modify_ts": 1778148697944
      }
    },
    {
      "id": "tieba_comments_316",
      "platform": "tieba",
      "file_type": "comments",
      "text": "有钱直接上贵点的LCD手机，一分钱一分货",
      "raw_data": {
        "comment_id": "153430764456",
        "parent_comment_id": "",
        "content": "有钱直接上贵点的LCD手机，一分钱一分货",
        "user_link": "https://tieba.baidu.com/home/main?id=tb.1.b27c6991.E8a-6MlD0wPq4PSgfmZsug%3Ft%3D1778148697",
        "user_nickname": "艾佐音",
        "user_avatar": "https://gss0.bdstatic.com/6LZ1dD3d1sgCo2Kml5_Y_D3/sys/portrait/item/tb.1.b27c6991.E8a-6MlD0wPq4PSgfmZsug?t=1778148697",
        "publish_time": "2026-04-18 14:17:39",
        "ip_location": "广东",
        "sub_comment_count": 13,
        "note_id": "10649112811",
        "note_url": "https://tieba.baidu.com/p/10649112811",
        "tieba_id": "26491947",
        "tieba_name": "关注屏幕健康吧",
        "tieba_link": "https://tieba.baidu.com/f?kw=%E5%85%B3%E6%B3%A8%E5%B1%8F%E5%B9%95%E5%81%A5%E5%BA%B7",
        "last_modify_ts": 1778148697944
      }
    },
    {
      "id": "tieba_comments_317",
      "platform": "tieba",
      "file_type": "comments",
      "text": "lz试一下我这个设置，我摸索出来的，多一格少一格都会更刺眼。",
      "raw_data": {
        "comment_id": "153432649188",
        "parent_comment_id": "",
        "content": "lz试一下我这个设置，我摸索出来的，多一格少一格都会更刺眼。",
        "user_link": "https://tieba.baidu.com/home/main?id=tb.1.89a152da.7tLZkuuc8hKucezlCghFnA%3Ft%3D1778148697",
        "user_nickname": "Juneau🎄",
        "user_avatar": "https://gss0.bdstatic.com/6LZ1dD3d1sgCo2Kml5_Y_D3/sys/portrait/item/tb.1.89a152da.7tLZkuuc8hKucezlCghFnA?t=1778148697",
        "publish_time": "2026-04-19 01:09:13",
        "ip_location": "辽宁",
        "sub_comment_count": 3,
        "note_id": "10649112811",
        "note_url": "https://tieba.baidu.com/p/10649112811",
        "tieba_id": "26491947",
        "tieba_name": "关注屏幕健康吧",
        "tieba_link": "https://tieba.baidu.com/f?kw=%E5%85%B3%E6%B3%A8%E5%B1%8F%E5%B9%95%E5%81%A5%E5%BA%B7",
        "last_modify_ts": 1778148697945
      }
    },
    {
      "id": "tieba_comments_318",
      "platform": "tieba",
      "file_type": "comments",
      "text": "试试y500i，眼睛不累，有nfc，至少不会让你地铁站罚站。",
      "raw_data": {
        "comment_id": "153440081898",
        "parent_comment_id": "",
        "content": "试试y500i，眼睛不累，有nfc，至少不会让你地铁站罚站。",
        "user_link": "https://tieba.baidu.com/home/main?id=tb.1.229501c.J5bPTLAVS65rhjbUcbukEQ%3Ft%3D1778148697",
        "user_nickname": "mexes_fr",
        "user_avatar": "https://gss0.bdstatic.com/6LZ1dD3d1sgCo2Kml5_Y_D3/sys/portrait/item/tb.1.229501c.J5bPTLAVS65rhjbUcbukEQ?t=1778148697",
        "publish_time": "2026-04-21 10:01:43",
        "ip_location": "上海",
        "sub_comment_count": 0,
        "note_id": "10649112811",
        "note_url": "https://tieba.baidu.com/p/10649112811",
        "tieba_id": "26491947",
        "tieba_name": "关注屏幕健康吧",
        "tieba_link": "https://tieba.baidu.com/f?kw=%E5%85%B3%E6%B3%A8%E5%B1%8F%E5%B9%95%E5%81%A5%E5%BA%B7",
        "last_modify_ts": 1778148697945
      }
    }
  ]
}